Workbook

Sheet 01_Referentiel_Unique
A1: RÉFÉRENTIEL ALGÉRIE POSTE — SERVICES ET CONDITIONS
A2: 75 lignes uniques, regroupées sans double comptage. La source est le texte transmis ; aucune date d'effet ou validation officielle n'a été fournie. Les montants 'non spécifiés' restent non chiffrés.
A4: ID stable | B4: Famille | C4: Sous-catégorie | D4: Service / opération | E4: Public | F4: Canal | G4: Nature information | H4: Tarif ou donnée (texte) | I4: Montant fixe DA | J4: Montant max DA | K4: Taux maximum | L4: Périodicité | M4: Plancher opération DA | N4: Plafond opération DA | O4: Période du plafond | P4: Délai réclamation jours | Q4: Délai réclamation mois | R4: Conditions / procédure | S4: Payeur | T4: Section d'origine | U4: Doublon fusionné | V4: Point à confirmer | W4: Colonne1 | X4: Colonne2 | Y4: Colonne3 | Z4: Colonne4
A5: AP-001 | B5: CCP & services financiers | C5: Comptes | D5: Ouverture d’un compte CCP | E5: Particulier | F5: Guichet | G5: TARIF | H5: Gratuit | I5: 0 | L5: À l’ouverture | R5: Pièce d'identité, formulaire CH1/CH2 ; bureau de poste desservant l'adresse | S5: Usager | T5: 7 | V5: Vérifier exigences documentaires pour particuliers/professionnels
A6: AP-002 | B6: CCP & services financiers | C6: Comptes | D6: Tenue de compte CCP | E6: Particulier | F6: Compte CCP | G6: TARIF | H6: Gratuit | I6: 0 | L6: Récurrent | S6: Usager | T6: 7 | V6: Confirmer conditions et exemptions
A7: AP-003 | B7: CCP & services financiers | C7: Caisse | D7: Retrait d'espèces au guichet CCP | E7: Particulier | F7: Guichet | G7: TARIF | H7: Gratuit | I7: 0 | L7: Par opération | R7: Pièce d’identité et livret CCP | S7: Usager | T7: 7
A8: AP-004 | B8: CCP & services financiers | C8: Caisse | D8: Versement d'espèces au guichet CCP | E8: Particulier | F8: Guichet | G8: TARIF | H8: Gratuit | I8: 0 | L8: Par opération | R8: Pièce d’identité et livret CCP | S8: Usager | T8: 7
A9: AP-005 | B9: CCP & services financiers | C9: Virements | D9: Virement entre comptes CCP | E9: Particulier | F9: Guichet / électronique | G9: TARIF | H9: Des frais peuvent s’appliquer | R9: Selon montant et destination | S9: Usager | T9: 7 | V9: Barème effectif et canal non détaillés
A10: AP-006 | B10: CCP & services financiers | C10: Paiement de factures | D10: Paiement de factures au guichet ou à distance | E10: Particulier | F10: Guichet / Barki@tic (cité) | G10: TARIF | H10: Gratuit | I10: 0 | L10: Par opération | R10: Présentation de la facture et du livret CCP au guichet | S10: Usager | T10: 7 | V10: Vérifier le nom du service numérique de paiement des factures ; Barki@tic est aussi décrit comme télégramme
A11: AP-007 | B11: Monétique EDAHABIA | C11: Gestion carte | D11: Réédition du code PIN EDAHABIA | E11: Porteur particulier | F11: Guichet / E-CCP / BaridiMob | G11: TARIF | H11: 200 DA | I11: 200 | L11: Par demande | R11: Sur demande | S11: Usager | T11: 7, 8 | U11: Section 7 et 8
A12: AP-008 | B12: Monétique EDAHABIA | C12: Gestion carte | D12: Blocage ou résiliation de la carte EDAHABIA | E12: Porteur particulier | F12: Guichet / service | G12: TARIF | H12: 30 DA | I12: 30 | L12: Par opération | S12: Usager | T12: 7, 8 | U12: Section 7 et 8
A13: AP-009 | B13: Monétique EDAHABIA | C13: Émission carte | D13: Création ou renouvellement EDAHABIA | E13: Porteur particulier | F13: Guichet / renouvellement auto | G13: TARIF | H13: 350 DA | I13: 350 | L13: Par carte / cycle annoncé de 2 ans | R13: Validité annoncée 2 ans ; renouvellement automatique ; comparaison avec carte « classique » 4 ans dans le texte | S13: Usager | T13: 7, 8 | U13: Section 7 et 8 | V13: Valider validité 2 ans vs mention 4 ans et prix exact
A14: AP-010 | B14: CCP & services financiers | C14: Documents | D14: Certificat bancaire CCP | E14: Particulier | F14: Guichet | G14: TARIF | H14: Non spécifié | S14: Usager | T14: 7 | V14: Tarif, pièces et délivrance à documenter
A15: AP-011 | B15: CCP & services financiers | C15: Documents | D15: Relevé de compte CCP | E15: Particulier | F15: Guichet / E-CCP | G15: TARIF | H15: Gratuit | I15: 0 | L15: Par demande | R15: Au guichet ou en ligne pour les utilisateurs avec accès électronique | S15: Usager | T15: 7 | V15: Confirmer gratuité selon format et canal
A16: AP-012 | B16: CCP & services financiers | C16: Chèques | D16: Perte ou vol du chéquier CCP | E16: Particulier | F16: Guichet | G16: PROCÉDURE | H16: Non spécifié | R16: Blocage immédiat et nouveau chéquier après vérification | S16: Usager | T16: 7 | V16: Vérifier frais de remplacement, délais et opposition
A17: AP-013 | B17: CCP & services financiers | C17: Épargne | D17: Compte épargne postal | E17: Particulier | F17: Bureau de poste | G17: TARIF | H17: Non spécifié | R17: Intérêts selon réglementation en vigueur | S17: Usager | T17: 7 | V17: Vérifier existence, opérateur, taux, conditions et distinction CCP/épargne
A18: AP-014 | B18: CCP & services financiers | C18: Épargne | D18: Plan d’épargne logement | E18: Particulier | F18: Bureau de poste | G18: TARIF | H18: Non spécifié | R18: Souscription auprès du bureau de poste | S18: Usager | T18: 7 | V18: Confirmer l’existence actuelle et modalités ; ne pas assimiler à crédit
A19: AP-015 | B19: CCP & services financiers | C19: Virements | D19: Virement permanent CCP | E19: Particulier | F19: Guichet / en ligne | G19: TARIF | H19: Non spécifié | R19: Transfert automatique ; demande avec signature autorisée | S19: Usager | T19: 7 | V19: Barème, disponibilité et fréquence à confirmer
A20: AP-016 | B20: CCP & services financiers | C20: Placements | D20: Produit d’investissement postal | E20: Particulier | F20: Bureau de poste | G20: TARIF | H20: Non spécifié | R20: Formulaire, pièces justificatives et dépôt initial | S20: Usager | T20: 7 | V20: Produit non identifié précisément : ne pas créer d’offre de placement sans nom/taux
A21: AP-017 | B21: International - remise reçue | C21: Transferts reçus | D21: Réception d'un transfert Western Union | E21: Tous publics | F21: Guichet | G21: TARIF | H21: Non spécifié | R21: Paiement en DZD ; maximum annoncé 500 000 DA ; pièce d’identité et MTCN obligatoires | S21: Usager | T21: 7 | V21: Vérifier plafond, disponibilité et nature du transfert : remise entrante seulement
A22: AP-018 | B22: CCP & services financiers | C22: Paiements pour tiers | D22: Paiement de prestations/factures pour tiers | E22: Tous publics | F22: Guichet | G22: TARIF | H22: Gratuit | I22: 0 | L22: Par paiement | R22: Téléphone, eau, électricité, SONELGAZ, BNP, ONEFD, EMS, TLS Contact, AFS, etc. | S22: Usager | T22: 7 | V22: Vérifier éventuelles exceptions par partenaire
A23: AP-019 | B23: CCP & services financiers | C23: Recharges | D23: Recharge téléphonique | E23: Tous publics | F23: Guichet / PDV | G23: TARIF | H23: Non spécifié | R23: Ooredoo, Djezzy, Mobilis, Assel ; Mobilis MASTER uniquement pour PDV | S23: Usager | T23: 7 | V23: Vérifier noms des opérateurs, restrictions et frais
A24: AP-020 | B24: CCP & services financiers | C24: Comptes | D24: Clôture de compte CCP | E24: Particulier | F24: Bureau de domiciliation | G24: TARIF | H24: Gratuit | I24: 0 | L24: Par clôture | R24: Pièce d'identité, formulaire de clôture ; restitution du solde | S24: Usager | T24: 7
A25: AP-021 | B25: CCP & services financiers | C25: Documents | D25: Renouvellement carte CCP ou livret | E25: Particulier | F25: Guichet | G25: TARIF | H25: Des frais peuvent s’appliquer | R25: Ancien livret/carte et pièce d’identité | S25: Usager | T25: 7 | V25: Produit de référence et tarif à préciser ; distinguer EDAHABIA
A26: AP-022 | B26: Services numériques | C26: E-CCP | D26: Accès au service CCP en ligne | E26: Particulier | F26: Web / smartphone | G26: TARIF | H26: Non spécifié | R26: Après inscription et activation ; solde, mouvements, transferts et paiement de factures | S26: Usager | T26: 7 | V26: Fonctions et tarification canal à confirmer
A27: AP-023 | B27: CCP & services financiers | C27: Réclamations | D27: Contester une opération CCP | E27: Particulier | F27: Bureau de poste | G27: PROCÉDURE | H27: Non spécifié | R27: Se rapprocher du bureau de poste | S27: Usager | T27: 7 | V27: Délai et pièces à préciser
A28: AP-024 | B28: Monétique EDAHABIA | C28: Retrait carte | D28: Retrait GAB Algérie Poste | E28: Porteur particulier | F28: GAB Algérie Poste | G28: TARIF | H28: 30 DA | I28: 30 | L28: Par retrait | S28: Usager | T28: 8
A29: AP-025 | B29: Monétique EDAHABIA | C29: Retrait carte | D29: Retrait GAB d'une banque | E29: Porteur particulier | F29: GAB bancaire interbancaire | G29: TARIF | H29: 35 DA | I29: 35 | L29: Par retrait | S29: Usager | T29: 8
A30: AP-026 | B30: Monétique EDAHABIA | C30: Retrait PIN PAD | D30: Retrait sur PIN PAD | E30: Porteur particulier | F30: PIN PAD | G30: TARIF | H30: 18 DA + barème progressif annoncé | I30: 18 | L30: Par retrait | R30: 18 DA fixe + 2 DA par 1 000 jusqu'à 18 000 ; 3 DA par 1 000 jusqu'à 1 000 000 ; 6 DA par 1 000 au-dessus. | S30: Usager | T30: 8 | V30: Calcul marginal/par tranche et arrondi des fractions de 1 000 non spécifiés ; simulation bloquée
A31: AP-027 | B31: Monétique EDAHABIA | C31: Paiement carte | D31: Paiement TPE avec EDAHABIA | E31: Porteur particulier | F31: TPE | G31: TARIF | H31: Gratuit pour le porteur | I31: 0 | L31: Par paiement | R31: Commission supportée par le commerçant | S31: Porteur | T31: 8 | V31: Vérifier périmètre de gratuité porteur
A32: AP-028 | B32: Monétique EDAHABIA | C32: Paiement carte | D32: Paiement en ligne EDAHABIA | E32: Porteur particulier | F32: E-commerce | G32: TARIF | H32: Gratuit pour le porteur | I32: 0 | L32: Par paiement | R32: Commission supportée par l’e-fournisseur | S32: Porteur | T32: 8
A33: AP-029 | B33: Monétique EDAHABIA | C33: Plafonds carte | D33: Plafond de retrait sur GAB | E33: Porteur particulier | F33: GAB | G33: PLAFOND | H33: 50 000 DA/jour | L33: Par jour | N33: 50000 | O33: Jour | S33: Usager | T33: 8
A34: AP-030 | B34: Monétique EDAHABIA | C34: Plafonds carte | D34: Plafond de paiement TPE | E34: Porteur particulier | F34: TPE | G34: PLAFOND | H34: 200 000 DA/jour | L34: Par jour | N34: 200000 | O34: Jour | S34: Usager | T34: 8
A35: AP-031 | B35: Monétique EDAHABIA | C35: Virement carte | D35: Virement CCP vers CCP via GAB | E35: Porteur particulier | F35: GAB | G35: PLAFOND | H35: De 1 000 à 50 000 DA/jour | L35: Par jour | M35: 1000 | N35: 50000 | O35: Jour | R35: Numéro RIP du bénéficiaire figurant sur le chèque bleu | S35: Usager | T35: 8 | V35: Frais de virement par GAB non spécifiés
A36: AP-032 | B36: Services numériques | C36: Virement mobile | D36: Virement CCP via BaridiMob | E36: Particulier | F36: BaridiMob | G36: PLAFOND | H36: De 1 000 à 200 000 DA/jour | L36: Par jour | M36: 1000 | N36: 200000 | O36: Jour | R36: Bénéficiaire peut retirer les fonds le jour même selon texte | S36: Usager | T36: 8 | V36: Plafond de 200 000 DA/jour à vérifier ; tarification décrite séparément section 9
A37: AP-033 | B37: Monétique EDAHABIA | C37: Information transaction | D37: Confirmation paiement en ligne | E37: Porteur particulier | F37: Site + SMS | G37: INFORMATION | H37: Non spécifié | R37: Reçu sur le site et SMS | S37: Usager | T37: 8
A38: AP-034 | B38: Monétique EDAHABIA | C38: Information transaction | D38: Confirmation paiement TPE | E38: Porteur particulier | F38: TPE + SMS | G38: INFORMATION | H38: Non spécifié | R38: Ticket de paiement et SMS | S38: Usager | T38: 8
A39: AP-035 | B39: Monétique EDAHABIA | C39: Réclamations | D39: Réclamation e-paiement | E39: Porteur particulier | F39: Fournisseur e-commerce | G39: PROCÉDURE | H39: Non spécifié | R39: Contacter e-fournisseur muni d’un ticket ou reçu | S39: Usager | T39: 8
A40: AP-036 | B40: Monétique EDAHABIA | C40: Réclamations | D40: Réclamation retrait sur GAB Algérie Poste | E40: Porteur particulier | F40: GAB Algérie Poste | G40: DÉLAI | H40: Délai non défini | R40: Recevabilité non précisée dans le texte | S40: Usager | T40: 8 | V40: Délai et procédure à obtenir
A41: AP-037 | B41: Monétique EDAHABIA | C41: Réclamations | D41: Réclamation retrait sur GAB bancaire | E41: Porteur particulier | F41: GAB banque | G41: DÉLAI | H41: 98 jours | P41: 98 | R41: Délai de recevabilité déclaré | S41: Usager | T41: 8
A42: AP-038 | B42: Monétique EDAHABIA | C42: Réclamations | D42: Réclamation e-paiement — opérateurs énumérés | E42: Porteur particulier | F42: E-commerce | G42: DÉLAI | H42: 45 jours | P42: 45 | R42: ATM Mobilis, Deazy, Caramma Assurance, CNRC, Macirvi, CAAT selon texte | S42: Usager | T42: 8 | V42: Orthographe/identité exacte des commerçants à confirmer
A43: AP-039 | B43: Monétique EDAHABIA | C43: Réclamations | D43: Réclamation e-paiement Algérie Télécom | E43: Porteur particulier | F43: E-commerce | G43: DÉLAI | H43: 90 jours | P43: 90 | S43: Usager | T43: 8
A44: AP-040 | B44: Monétique EDAHABIA | C44: Réclamations | D44: Réclamation e-paiement Air Algérie | E44: Porteur particulier | F44: E-commerce | G44: DÉLAI | H44: 120 jours | P44: 120 | S44: Usager | T44: 8
A45: AP-041 | B45: Monétique EDAHABIA | C45: Réseaux | D45: Utilisation EDAHABIA sur GAB de banques | E45: Porteur particulier | F45: Interbancaire | G45: INFORMATION | H45: Non spécifié | R45: Utilisation interbancaire | S45: Usager | T45: 8 | V45: Accès selon réseau et compatibilité
A46: AP-042 | B46: Identifiants et référentiels | C46: RIP | D46: RIP utilisé pour virement GAB | E46: Tous publics | F46: GAB / chèque bleu | G46: DÉFINITION | H46: Non applicable | R46: Le numéro RIP est mentionné sur le chèque bleu | S46: Usager | T46: 8
A47: AP-043 | B47: Identifiants et référentiels | C47: RIP | D47: Définition RIP | E47: Tous publics | F47: Compte CCP | G47: DÉFINITION | H47: Non applicable | R47: Identifiant du compte postal ; texte cite nom, prénom, adresse, NIP | S47: Usager | T47: 8 | V47: Vérifier composition normative et présentation exacte du RIP
A48: AP-044 | B48: Identifiants et référentiels | C48: NIP | D48: Définition NIP | E48: Tous publics | F48: Compte CCP | G48: DÉFINITION | H48: Non applicable | R48: Le texte indique code banque 007, code agence 99999, numéro de compte CCP et clé | S48: Usager | T48: 8 | V48: Contrôler terminologie et structure des identifiants (RIP/NIP)
A49: AP-045 | B49: Identifiants et référentiels | C49: RIP | D49: Utilité du RIP | E49: Tous publics | F49: Virements / interbancaire | G49: DÉFINITION | H49: Non applicable | R49: Coordonnées du compte postal pour GAB, BaridiMob et autres opérations | S49: Usager | T49: 8
A50: AP-046 | B50: Monétique EDAHABIA | C50: Paiement factures | D50: Paiement de factures avec EDAHABIA | E50: Porteur particulier | F50: Carte / services conventionnés | G50: INFORMATION | H50: Non spécifié | R50: Factures d’opérateurs conventionnés listés sur le site Algérie Poste | S50: Usager | T50: 8 | V50: Liste fournisseurs et éventuels frais à confirmer
A51: AP-047 | B51: Monétique EDAHABIA | C51: Suivi des opérations | D51: Relevé opérations carte à la poste | E51: Porteur particulier | F51: Guichet | G51: INFORMATION | H51: Non spécifié | R51: Relevé pour la période souhaitée | S51: Usager | T51: 8
A52: AP-048 | B52: Monétique EDAHABIA | C52: Suivi des opérations | D52: Mini-relevé de carte | E52: Porteur particulier | F52: Réseau GAB bancaire | G52: INFORMATION | H52: Non spécifié | R52: Dix dernières transactions | S52: Usager | T52: 8
A53: AP-049 | B53: Monétique EDAHABIA | C53: Suivi des opérations | D53: Relevé complet de carte | E53: Porteur particulier | F53: Site Algérie Poste / E-CCP | G53: INFORMATION | H53: Non spécifié | R53: Relevé complet accessible en ligne selon le texte | S53: Usager | T53: 8
A54: AP-050 | B54: Monétique EDAHABIA | C54: Incidents carte | D54: Carte oubliée dans un GAB | E54: Porteur particulier | F54: GAB | G54: PROCÉDURE | H54: Non spécifié | R54: Carte capturée par l’automate ; contacter l’établissement postal pour la récupérer | S54: Usager | T54: 8
A55: AP-051 | B55: Monétique TPE commerçants | C55: Équipement TPE | D55: Acquisition / mise à disposition du TPE mobile | E55: Professionnel / Entreprise | F55: TPE mobile | G55: TARIF | H55: Gratuit | I55: 0 | L55: À la mise à disposition | R55: Abonnement mensuel distinct de 800 DA HT | S55: Commerçant | T55: 8, 9 | U55: Section 8 et 9 | V55: Vérifier gratuité de matériel, dépôt de garantie et modalités d’installation
A56: AP-052 | B56: Monétique TPE commerçants | C56: Abonnement TPE | D56: Abonnement TPE mobile | E56: Professionnel / Entreprise | F56: TPE mobile | G56: TARIF | H56: 800 DA HT / mois | I56: 800 | L56: Mensuelle | R56: 300 DA gestion + 300 DA connectivité + 200 DA adhésion Algérie Poste | S56: Commerçant | T56: 8, 9 | U56: Section 8 et 9 | V56: Confirmer base HT et éventuel assujettissement TVA
A57: AP-053 | B57: Monétique TPE commerçants | C57: Frais commerçant | D57: Commission transaction sur TPE | E57: Professionnel / Entreprise | F57: TPE | G57: TARIF | H57: Jusqu’à 1,50 % du montant | K57: 0.015 | L57: Par transaction | R57: Taux exact selon barème non communiqué | S57: Commerçant | T57: 8, 9 | U57: Section 8 et 9 | V57: Plafond uniquement, pas de taux fixe exploitable pour tous
A58: AP-054 | B58: Monétique TPE commerçants | C58: Administration TPE | D58: Déménagement / modification adresse TPE | E58: Professionnel / Entreprise | F58: Courrier DUPW | G58: TARIF | H58: Gratuit | I58: 0 | L58: Par demande | R58: Courrier à la Direction d’Unité Postale de Wilaya : ancienne et nouvelle adresse, nouveau numéro de téléphone | S58: Commerçant | T58: 8, 9 | U58: Section 8 et 9
A59: AP-055 | B59: Monétique TPE commerçants | C59: Fonctions TPE | D59: Fonctions réalisables sur un TPE | E59: Professionnel / Entreprise | F59: TPE | G59: INFORMATION | H59: Non spécifié | R59: Vente, annulation, remboursement, cash advance | S59: Commerçant | T59: 8 | V59: Confirmer disponibilité du cash advance et de chaque fonctionnalité TPE
A60: AP-056 | B60: Réseau et services postaux | C60: Boîtes postales | D60: Abonnement boîte postale — personne physique | E60: Particulier | F60: Bureau de poste | G60: TARIF | H60: 1 000 DA / an | I60: 1000 | L60: Annuelle | R60: Tacite reconduction ; renouvellement à partir du 15 décembre | S60: Usager | T60: 9
A61: AP-057 | B61: Réseau et services postaux | C61: Boîtes postales | D61: Abonnement boîte postale — personne morale | E61: Professionnel / Entreprise | F61: Bureau de poste | G61: TARIF | H61: 4 200 DA / an | I61: 4200 | L61: Annuelle | R61: Tacite reconduction ; renouvellement à partir du 15 décembre | S61: Usager | T61: 9
A62: AP-058 | B62: Monétique TPE commerçants | C62: Détail abonnement | D62: Composante abonnement TPE — gestion | E62: Professionnel / Entreprise | F62: TPE mobile | G62: TARIF | H62: 300 DA HT / mois | I62: 300 | L62: Mensuelle | R62: Composante du forfait TPE à 800 DA HT/mois : ne pas additionner si forfait retenu | S62: Commerçant | T62: 9 | V62: Inclus dans 800 DA HT mensuels
A63: AP-059 | B63: Monétique TPE commerçants | C63: Détail abonnement | D63: Composante abonnement TPE — connectivité | E63: Professionnel / Entreprise | F63: TPE mobile | G63: TARIF | H63: 300 DA HT / mois | I63: 300 | L63: Mensuelle | R63: Composante du forfait TPE à 800 DA HT/mois : ne pas additionner si forfait retenu | S63: Commerçant | T63: 9 | V63: Inclus dans 800 DA HT mensuels
A64: AP-060 | B64: Monétique TPE commerçants | C64: Détail abonnement | D64: Composante abonnement TPE — adhésion Algérie Poste | E64: Professionnel / Entreprise | F64: TPE mobile | G64: TARIF | H64: 200 DA HT / mois | I64: 200 | L64: Mensuelle | R64: Composante du forfait TPE à 800 DA HT/mois : ne pas additionner si forfait retenu | S64: Commerçant | T64: 9 | V64: Inclus dans 800 DA HT mensuels
A65: AP-061 | B65: Services numériques | C65: BaridiMob | D65: Adhésion BaridiMob | E65: Particulier | F65: Application BaridiMob | G65: TARIF | H65: 50 DA | I65: 50 | L65: À l’adhésion | S65: Usager | T65: 9 | V65: Barème canal/applicable à vérifier
A66: AP-062 | B66: Services numériques | C66: BaridiMob | D66: Virement via BaridiMob — frais | E66: Particulier | F66: Application BaridiMob | G66: TARIF | H66: 12 à 24 DA / virement | I66: 12 | J66: 24 | L66: Par virement | R66: Tranches de montant non indiquées dans le texte | S66: Usager | T66: 9 | V66: Barème détaillé par tranche à obtenir avant calcul exact
A67: AP-063 | B67: Services numériques | C67: BaridiMob | D67: Abonnement mensuel BaridiMob | E67: Particulier | F67: Application BaridiMob | G67: TARIF | H67: 50 DA / mois | I67: 50 | L67: Mensuelle | S67: Usager | T67: 9 | V67: Vérifier caractère automatique/optionnel
A68: AP-064 | B68: Réseau et services postaux | C68: Réexpédition courrier | D68: Réexpédition de courrier — temporaire | E68: Tous publics | F68: Bureau de poste | G68: PROCÉDURE | H68: Non spécifié | R68: Modèle 755A ; changement temporaire indiqué 3 mois ; prolongations payantes possibles | S68: Usager | T68: 9 | V68: Tarif exact et règles de prolongation non fournis
A69: AP-065 | B69: Réseau et services postaux | C69: Réexpédition courrier | D69: Réexpédition de courrier — définitive | E69: Tous publics | F69: Bureau de poste | G69: PROCÉDURE | H69: Non spécifié | R69: Modèle 755B ; durée indiquée 1 an ; prolongations payantes possibles | S69: Usager | T69: 9 | V69: Durées (« poste restante » dans le texte) et tarif à confirmer
A70: AP-066 | B70: Réseau et services postaux | C70: Poste restante | D70: Poste restante — journaux | E70: Tous publics | F70: Poste restante | G70: TARIF | H70: 30 DA | I70: 30 | L70: Par objet | R70: Garde maximale annoncée : 1 mois | S70: Usager | T70: 9 | V70: Unité exacte du prix à confirmer
A71: AP-067 | B71: Réseau et services postaux | C71: Poste restante | D71: Poste restante — autres objets | E71: Tous publics | F71: Poste restante | G71: TARIF | H71: 55 DA | I71: 55 | L71: Par objet | R71: Garde maximale annoncée : 1 mois | S71: Usager | T71: 9 | V71: Unité exacte du prix à confirmer
A72: AP-068 | B72: Réseau et services postaux | C72: Poste restante | D72: Abonnement annuel poste restante | E72: Tous publics | F72: Poste restante | G72: TARIF | H72: 2 000 DA / an | I72: 2000 | L72: Annuelle | R72: Carte d'abonnement valable 1 an | S72: Usager | T72: 9
A73: AP-069 | B73: Réseau et services postaux | C73: Procurations | D73: Procuration postale | E73: Tous publics | F73: Guichet / notaire | G73: TARIF | H73: Droit de timbre | R73: Modèle 776 ou procuration notariée ; valable uniquement pour l’établissement dépositaire | S73: Usager | T73: 9 | V73: Montant droit de timbre et portée juridique à confirmer
A74: AP-070 | B74: Réseau et services postaux | C74: Télégrammes | D74: Service Barki@tic | E74: Tous publics | F74: Tout bureau / convention entreprise | G74: TARIF | H74: Non spécifié | R74: Envoi de télégrammes électroniques ; personnes physiques : bureau ; personnes morales : convention avec DUPW | S74: Usager | T74: 9 | V74: Clarifier discordance avec mention de Barki@tic pour paiement de factures (§7)
A75: AP-071 | B75: Réseau et services postaux | C75: Produits à valeur ajoutée | D75: Produits à valeur ajoutée postaux | E75: Tous publics | F75: Bureau de poste | G75: TARIF | H75: Non spécifié | R75: Vignettes auto, timbres fiscaux/amendes/poste, pages MAGHREB, pochettes philatéliques | S75: Usager | T75: 9 | V75: Chaque produit doit avoir son tarif propre si intégré ultérieurement
A76: AP-072 | B76: Réseau et services postaux | C76: Philatélie | D76: Abonnement philatélique | E76: Tous publics | F76: Recette principale | G76: TARIF | H76: Abonnement mensuel — montant non indiqué | L76: Mensuelle | R76: Souscription locale, versement mensuel, envoi du timbre du 1er jour par recommandé | S76: Usager | T76: 9 | V76: Prix, conditions d’envoi et frais postaux manquants
A77: AP-073 | B77: Réseau et services postaux | C77: Réclamations | D77: Réclamation courrier recommandé domestique non reçu | E77: Tous publics | F77: Formulaire N°846 | G77: DÉLAI | H77: Délai : 1 an | P77: 365 | R77: À compter du lendemain de la date de dépôt | S77: Usager | T77: 9
A78: AP-074 | B78: Réseau et services postaux | C78: Réclamations | D78: Réclamation courrier recommandé international non reçu | E78: Tous publics | F78: Formulaire CN08 | G78: DÉLAI | H78: Délai : 6 mois | Q78: 6 | R78: À compter du lendemain de la date de dépôt | S78: Usager | T78: 9 | V78: Ne pas convertir automatiquement les 6 mois en un nombre fixe de jours
A79: AP-075 | B79: Réseau et services postaux | C79: Codes postaux | D79: Consultation du code postal | E79: Tous publics | F79: www.poste.dz / guichet | G79: TARIF | H79: Gratuit | I79: 0 | L79: Par consultation | R79: Recherche sur poste.dz ou au bureau de poste de résidence | S79: Usager | T79: 9

Sheet 02_CCP_Comptes
A1: CCP : ouverture, tenue, caisse, virements, épargne et chèques
A2: Distinguer les comptes CCP des éventuels produits d'épargne postale : aucun taux non fourni n'est complété.
A4: ID | B4: Sous-catégorie | C4: Service / information | D4: Public | E4: Canal | F4: Tarif annoncé | G4: Montant DA | H4: Max DA | I4: % max | J4: Fréquence | K4: Conditions / procédure | L4: Section | M4: Vérification nécessaire | N4: Type
A5: AP-001 | B5: Comptes | C5: Ouverture d’un compte CCP | D5: Particulier | E5: Guichet | F5: Gratuit | G5: 0 | J5: À l’ouverture | K5: Pièce d'identité, formulaire CH1/CH2 ; bureau de poste desservant l'adresse | L5: 7 | M5: Vérifier exigences documentaires pour particuliers/professionnels | N5: TARIF
A6: AP-002 | B6: Comptes | C6: Tenue de compte CCP | D6: Particulier | E6: Compte CCP | F6: Gratuit | G6: 0 | J6: Récurrent | L6: 7 | M6: Confirmer conditions et exemptions | N6: TARIF
A7: AP-003 | B7: Caisse | C7: Retrait d'espèces au guichet CCP | D7: Particulier | E7: Guichet | F7: Gratuit | G7: 0 | J7: Par opération | K7: Pièce d’identité et livret CCP | L7: 7 | M7: Confirmer date et tarif sur source officielle | N7: TARIF
A8: AP-004 | B8: Caisse | C8: Versement d'espèces au guichet CCP | D8: Particulier | E8: Guichet | F8: Gratuit | G8: 0 | J8: Par opération | K8: Pièce d’identité et livret CCP | L8: 7 | M8: Confirmer date et tarif sur source officielle | N8: TARIF
A9: AP-005 | B9: Virements | C9: Virement entre comptes CCP | D9: Particulier | E9: Guichet / électronique | F9: Des frais peuvent s’appliquer | K9: Selon montant et destination | L9: 7 | M9: Barème effectif et canal non détaillés | N9: TARIF
A10: AP-006 | B10: Paiement de factures | C10: Paiement de factures au guichet ou à distance | D10: Particulier | E10: Guichet / Barki@tic (cité) | F10: Gratuit | G10: 0 | J10: Par opération | K10: Présentation de la facture et du livret CCP au guichet | L10: 7 | M10: Vérifier le nom du service numérique de paiement des factures ; Barki@tic est aussi décrit comme télégramme | N10: TARIF
A11: AP-010 | B11: Documents | C11: Certificat bancaire CCP | D11: Particulier | E11: Guichet | F11: Non spécifié | L11: 7 | M11: Tarif, pièces et délivrance à documenter | N11: TARIF
A12: AP-011 | B12: Documents | C12: Relevé de compte CCP | D12: Particulier | E12: Guichet / E-CCP | F12: Gratuit | G12: 0 | J12: Par demande | K12: Au guichet ou en ligne pour les utilisateurs avec accès électronique | L12: 7 | M12: Confirmer gratuité selon format et canal | N12: TARIF
A13: AP-012 | B13: Chèques | C13: Perte ou vol du chéquier CCP | D13: Particulier | E13: Guichet | F13: Non spécifié | K13: Blocage immédiat et nouveau chéquier après vérification | L13: 7 | M13: Vérifier frais de remplacement, délais et opposition | N13: PROCÉDURE
A14: AP-013 | B14: Épargne | C14: Compte épargne postal | D14: Particulier | E14: Bureau de poste | F14: Non spécifié | K14: Intérêts selon réglementation en vigueur | L14: 7 | M14: Vérifier existence, opérateur, taux, conditions et distinction CCP/épargne | N14: TARIF
A15: AP-014 | B15: Épargne | C15: Plan d’épargne logement | D15: Particulier | E15: Bureau de poste | F15: Non spécifié | K15: Souscription auprès du bureau de poste | L15: 7 | M15: Confirmer l’existence actuelle et modalités ; ne pas assimiler à crédit | N15: TARIF
A16: AP-015 | B16: Virements | C16: Virement permanent CCP | D16: Particulier | E16: Guichet / en ligne | F16: Non spécifié | K16: Transfert automatique ; demande avec signature autorisée | L16: 7 | M16: Barème, disponibilité et fréquence à confirmer | N16: TARIF
A17: AP-016 | B17: Placements | C17: Produit d’investissement postal | D17: Particulier | E17: Bureau de poste | F17: Non spécifié | K17: Formulaire, pièces justificatives et dépôt initial | L17: 7 | M17: Produit non identifié précisément : ne pas créer d’offre de placement sans nom/taux | N17: TARIF
A18: AP-018 | B18: Paiements pour tiers | C18: Paiement de prestations/factures pour tiers | D18: Tous publics | E18: Guichet | F18: Gratuit | G18: 0 | J18: Par paiement | K18: Téléphone, eau, électricité, SONELGAZ, BNP, ONEFD, EMS, TLS Contact, AFS, etc. | L18: 7 | M18: Vérifier éventuelles exceptions par partenaire | N18: TARIF
A19: AP-019 | B19: Recharges | C19: Recharge téléphonique | D19: Tous publics | E19: Guichet / PDV | F19: Non spécifié | K19: Ooredoo, Djezzy, Mobilis, Assel ; Mobilis MASTER uniquement pour PDV | L19: 7 | M19: Vérifier noms des opérateurs, restrictions et frais | N19: TARIF
A20: AP-020 | B20: Comptes | C20: Clôture de compte CCP | D20: Particulier | E20: Bureau de domiciliation | F20: Gratuit | G20: 0 | J20: Par clôture | K20: Pièce d'identité, formulaire de clôture ; restitution du solde | L20: 7 | M20: Confirmer date et tarif sur source officielle | N20: TARIF
A21: AP-021 | B21: Documents | C21: Renouvellement carte CCP ou livret | D21: Particulier | E21: Guichet | F21: Des frais peuvent s’appliquer | K21: Ancien livret/carte et pièce d’identité | L21: 7 | M21: Produit de référence et tarif à préciser ; distinguer EDAHABIA | N21: TARIF
A22: AP-023 | B22: Réclamations | C22: Contester une opération CCP | D22: Particulier | E22: Bureau de poste | F22: Non spécifié | K22: Se rapprocher du bureau de poste | L22: 7 | M22: Délai et pièces à préciser | N22: PROCÉDURE

Sheet 03_EDAHABIA
A1: Carte EDAHABIA : monétique, paiements, plafonds et réclamations
A2: Les tarifs du porteur et les plafonds sont deux types d'informations distincts. Les frais de PIN et de carte sont dédupliqués entre sections 7 et 8.
A4: ID | B4: Sous-catégorie | C4: Service / information | D4: Public | E4: Canal | F4: Tarif annoncé | G4: Montant DA | H4: Max DA | I4: % max | J4: Fréquence | K4: Conditions / procédure | L4: Section | M4: Vérification nécessaire | N4: Type
A5: AP-007 | B5: Gestion carte | C5: Réédition du code PIN EDAHABIA | D5: Porteur particulier | E5: Guichet / E-CCP / BaridiMob | F5: 200 DA | G5: 200 | J5: Par demande | K5: Sur demande | L5: 7, 8 | M5: Confirmer date et tarif sur source officielle | N5: TARIF
A6: AP-008 | B6: Gestion carte | C6: Blocage ou résiliation de la carte EDAHABIA | D6: Porteur particulier | E6: Guichet / service | F6: 30 DA | G6: 30 | J6: Par opération | L6: 7, 8 | N6: TARIF
A7: AP-009 | B7: Émission carte | C7: Création ou renouvellement EDAHABIA | D7: Porteur particulier | E7: Guichet / renouvellement auto | F7: 350 DA | G7: 350 | J7: Par carte / cycle annoncé de 2 ans | K7: Validité annoncée 4 ans ; renouvellement automatique ; | L7: 7, 8 | N7: TARIF
A8: AP-024 | B8: Retrait carte | C8: Retrait GAB Algérie Poste | D8: Porteur particulier | E8: GAB Algérie Poste | F8: 30 DA | G8: 30 | J8: Par retrait | L8: 8 | N8: TARIF
A9: AP-025 | B9: Retrait carte | C9: Retrait GAB d'une banque | D9: Porteur particulier | E9: GAB bancaire interbancaire | F9: 35 DA | G9: 35 | J9: Par retrait | L9: 8 | N9: TARIF
A10: AP-026 | B10: Retrait PIN PAD | C10: Retrait sur PIN PAD | D10: Porteur particulier | E10: PIN PAD | F10: 18 DA + barème progressif annoncé | G10: 18 | J10: Par retrait | K10: 18 DA fixe + 2 DA par 1 000 jusqu'à 18 000 ; 3 DA par 1 000 jusqu'à 1 000 000 ; 6 DA par 1 000 au-dessus. | L10: 8 | M10: Calcul marginal/par tranche et arrondi des fractions de 1 000 non spécifiés ; simulation bloquée | N10: TARIF
A11: AP-027 | B11: Paiement carte | C11: Paiement TPE avec EDAHABIA | D11: Porteur particulier | E11: TPE | F11: Gratuit pour le porteur | G11: 0 | J11: Par paiement | K11: Commission supportée par le commerçant | L11: 8 | M11: Vérifier périmètre de gratuité porteur | N11: TARIF
A12: AP-028 | B12: Paiement carte | C12: Paiement en ligne EDAHABIA | D12: Porteur particulier | E12: E-commerce | F12: Gratuit pour le porteur | G12: 0 | J12: Par paiement | K12: Commission supportée par l’e-fournisseur | L12: 8 | M12: Confirmer date et tarif sur source officielle | N12: TARIF
A13: AP-029 | B13: Plafonds carte | C13: Plafond de retrait sur GAB | D13: Porteur particulier | E13: GAB | F13: 50 000 DA/jour | J13: Par jour | L13: 8 | M13: Confirmer date et tarif sur source officielle | N13: PLAFOND
A14: AP-030 | B14: Plafonds carte | C14: Plafond de paiement TPE | D14: Porteur particulier | E14: TPE | F14: 200 000 DA/jour | J14: Par jour | L14: 8 | M14: Confirmer date et tarif sur source officielle | N14: PLAFOND
A15: AP-031 | B15: Virement carte | C15: Virement CCP vers CCP via GAB | D15: Porteur particulier | E15: GAB | F15: De 1 000 à 50 000 DA/jour | J15: Par jour | K15: Numéro RIP du bénéficiaire figurant sur le chèque bleu | L15: 8 | M15: Frais de virement par GAB non spécifiés | N15: PLAFOND
A16: AP-033 | B16: Information transaction | C16: Confirmation paiement en ligne | D16: Porteur particulier | E16: Site + SMS | F16: Non spécifié | K16: Reçu sur le site et SMS | L16: 8 | M16: Confirmer date et tarif sur source officielle | N16: INFORMATION
A17: AP-034 | B17: Information transaction | C17: Confirmation paiement TPE | D17: Porteur particulier | E17: TPE + SMS | F17: Non spécifié | K17: Ticket de paiement et SMS | L17: 8 | M17: Confirmer date et tarif sur source officielle | N17: INFORMATION
A18: AP-035 | B18: Réclamations | C18: Réclamation e-paiement | D18: Porteur particulier | E18: Fournisseur e-commerce | F18: Non spécifié | K18: Contacter e-fournisseur muni d’un ticket ou reçu | L18: 8 | M18: Confirmer date et tarif sur source officielle | N18: PROCÉDURE
A19: AP-036 | B19: Réclamations | C19: Réclamation retrait sur GAB Algérie Poste | D19: Porteur particulier | E19: GAB Algérie Poste | F19: Délai non défini | K19: Recevabilité non précisée dans le texte | L19: 8 | M19: Délai et procédure à obtenir | N19: DÉLAI
A20: AP-037 | B20: Réclamations | C20: Réclamation retrait sur GAB bancaire | D20: Porteur particulier | E20: GAB banque | F20: 98 jours | K20: Délai de recevabilité déclaré | L20: 8 | M20: Confirmer date et tarif sur source officielle | N20: DÉLAI
A21: AP-038 | B21: Réclamations | C21: Réclamation e-paiement — opérateurs énumérés | D21: Porteur particulier | E21: E-commerce | F21: 45 jours | K21: ATM Mobilis, Deazy, Caramma Assurance, CNRC, Macirvi, CAAT selon texte | L21: 8 | M21: Orthographe/identité exacte des commerçants à confirmer | N21: DÉLAI
A22: AP-039 | B22: Réclamations | C22: Réclamation e-paiement Algérie Télécom | D22: Porteur particulier | E22: E-commerce | F22: 90 jours | L22: 8 | M22: Confirmer date et tarif sur source officielle | N22: DÉLAI
A23: AP-040 | B23: Réclamations | C23: Réclamation e-paiement Air Algérie | D23: Porteur particulier | E23: E-commerce | F23: 120 jours | L23: 8 | M23: Confirmer date et tarif sur source officielle | N23: DÉLAI
A24: AP-041 | B24: Réseaux | C24: Utilisation EDAHABIA sur GAB de banques | D24: Porteur particulier | E24: Interbancaire | F24: Non spécifié | K24: Utilisation interbancaire | L24: 8 | M24: Accès selon réseau et compatibilité | N24: INFORMATION
A25: AP-046 | B25: Paiement factures | C25: Paiement de factures avec EDAHABIA | D25: Porteur particulier | E25: Carte / services conventionnés | F25: Non spécifié | K25: Factures d’opérateurs conventionnés listés sur le site Algérie Poste | L25: 8 | M25: Liste fournisseurs et éventuels frais à confirmer | N25: INFORMATION
A26: AP-047 | B26: Suivi des opérations | C26: Relevé opérations carte à la poste | D26: Porteur particulier | E26: Guichet | F26: Non spécifié | K26: Relevé pour la période souhaitée | L26: 8 | M26: Confirmer date et tarif sur source officielle | N26: INFORMATION
A27: AP-048 | B27: Suivi des opérations | C27: Mini-relevé de carte | D27: Porteur particulier | E27: Réseau GAB bancaire | F27: Non spécifié | K27: Dix dernières transactions | L27: 8 | M27: Confirmer date et tarif sur source officielle | N27: INFORMATION
A28: AP-049 | B28: Suivi des opérations | C28: Relevé complet de carte | D28: Porteur particulier | E28: Site Algérie Poste / E-CCP | F28: Non spécifié | K28: Relevé complet accessible en ligne selon le texte | L28: 8 | M28: Confirmer date et tarif sur source officielle | N28: INFORMATION
A29: AP-050 | B29: Incidents carte | C29: Carte oubliée dans un GAB | D29: Porteur particulier | E29: GAB | F29: Non spécifié | K29: Carte capturée par l’automate ; contacter l’établissement postal pour la récupérer | L29: 8 | M29: Confirmer date et tarif sur source officielle | N29: PROCÉDURE

Sheet 04_TPE_Commercants
A1: TPE MOBILE : TARIFS ET SERVICES AUX COMMERÇANTS
A2: Le forfait de 800 DA HT comprend 300 + 300 + 200 DA : les composantes ne doivent jamais être additionnées une seconde fois.
A4: ID | B4: Sous-catégorie | C4: Service / information | D4: Public | E4: Canal | F4: Tarif annoncé | G4: Montant DA | H4: Max DA | I4: % max | J4: Fréquence | K4: Conditions / procédure | L4: Section | M4: Vérification nécessaire | N4: Type
A5: AP-051 | B5: Équipement TPE | C5: Acquisition / mise à disposition du TPE mobile | D5: Professionnel / Entreprise | E5: TPE mobile | F5: Gratuit | G5: 0 | J5: À la mise à disposition | K5: Abonnement mensuel distinct de 800 DA HT | L5: 8, 9 | M5: Vérifier gratuité de matériel, dépôt de garantie et modalités d’installation | N5: TARIF
A6: AP-052 | B6: Abonnement TPE | C6: Abonnement TPE mobile | D6: Professionnel / Entreprise | E6: TPE mobile | F6: 800 DA HT / mois | G6: 800 | J6: Mensuelle | K6: 300 DA gestion + 300 DA connectivité + 200 DA adhésion Algérie Poste | L6: 8, 9 | M6: Confirmer base HT et éventuel assujettissement TVA | N6: TARIF
A7: AP-053 | B7: Frais commerçant | C7: Commission transaction sur TPE | D7: Professionnel / Entreprise | E7: TPE | F7: Jusqu’à 1,50 % du montant | I7: 0.015 | J7: Par transaction | K7: Taux exact selon barème non communiqué | L7: 8, 9 | M7: Plafond uniquement, pas de taux fixe exploitable pour tous | N7: TARIF
A8: AP-054 | B8: Administration TPE | C8: Déménagement / modification adresse TPE | D8: Professionnel / Entreprise | E8: Courrier DUPW | F8: Gratuit | G8: 0 | J8: Par demande | K8: Courrier à la Direction d’Unité Postale de Wilaya : ancienne et nouvelle adresse, nouveau numéro de téléphone | L8: 8, 9 | M8: Confirmer date et tarif sur source officielle | N8: TARIF
A9: AP-055 | B9: Fonctions TPE | C9: Fonctions réalisables sur un TPE | D9: Professionnel / Entreprise | E9: TPE | F9: Non spécifié | K9: Vente, annulation, remboursement, cash advance | L9: 8 | M9: Confirmer disponibilité du cash advance et de chaque fonctionnalité TPE | N9: INFORMATION
A10: AP-058 | B10: Détail abonnement | C10: Composante abonnement TPE — gestion | D10: Professionnel / Entreprise | E10: TPE mobile | F10: 300 DA HT / mois | G10: 300 | J10: Mensuelle | K10: Composante du forfait TPE à 800 DA HT/mois : ne pas additionner si forfait retenu | L10: 9 | M10: Inclus dans 800 DA HT mensuels | N10: TARIF
A11: AP-059 | B11: Détail abonnement | C11: Composante abonnement TPE — connectivité | D11: Professionnel / Entreprise | E11: TPE mobile | F11: 300 DA HT / mois | G11: 300 | J11: Mensuelle | K11: Composante du forfait TPE à 800 DA HT/mois : ne pas additionner si forfait retenu | L11: 9 | M11: Inclus dans 800 DA HT mensuels | N11: TARIF
A12: AP-060 | B12: Détail abonnement | C12: Composante abonnement TPE — adhésion Algérie Poste | D12: Professionnel / Entreprise | E12: TPE mobile | F12: 200 DA HT / mois | G12: 200 | J12: Mensuelle | K12: Composante du forfait TPE à 800 DA HT/mois : ne pas additionner si forfait retenu | L12: 9 | M12: Inclus dans 800 DA HT mensuels | N12: TARIF

Sheet 05_Reseau_Postal
A1: SERVICES POSTAUX : BOÎTES, COURRIER ET POSTE RESTANTE
A2: La location de boîte postale et les services de courrier sont séparés des frais du compte CCP.
A4: ID | B4: Sous-catégorie | C4: Service / information | D4: Public | E4: Canal | F4: Tarif annoncé | G4: Montant DA | H4: Max DA | I4: % max | J4: Fréquence | K4: Conditions / procédure | L4: Section | M4: Vérification nécessaire | N4: Type
A5: AP-056 | B5: Boîtes postales | C5: Abonnement boîte postale — personne physique | D5: Particulier | E5: Bureau de poste | F5: 1 000 DA / an | G5: 1000 | J5: Annuelle | K5: Tacite reconduction ; renouvellement à partir du 15 décembre | L5: 9 | M5: Confirmer date et tarif sur source officielle | N5: TARIF
A6: AP-057 | B6: Boîtes postales | C6: Abonnement boîte postale — personne morale | D6: Professionnel / Entreprise | E6: Bureau de poste | F6: 4 200 DA / an | G6: 4200 | J6: Annuelle | K6: Tacite reconduction ; renouvellement à partir du 15 décembre | L6: 9 | M6: Confirmer date et tarif sur source officielle | N6: TARIF
A7: AP-064 | B7: Réexpédition courrier | C7: Réexpédition de courrier — temporaire | D7: Tous publics | E7: Bureau de poste | F7: Non spécifié | K7: Modèle 755A ; changement temporaire indiqué 3 mois ; prolongations payantes possibles | L7: 9 | M7: Tarif exact et règles de prolongation non fournis | N7: PROCÉDURE
A8: AP-065 | B8: Réexpédition courrier | C8: Réexpédition de courrier — définitive | D8: Tous publics | E8: Bureau de poste | F8: Non spécifié | K8: Modèle 755B ; durée indiquée 1 an ; prolongations payantes possibles | L8: 9 | M8: Durées (« poste restante » dans le texte) et tarif à confirmer | N8: PROCÉDURE
A9: AP-066 | B9: Poste restante | C9: Poste restante — journaux | D9: Tous publics | E9: Poste restante | F9: 30 DA | G9: 30 | J9: Par objet | K9: Garde maximale annoncée : 1 mois | L9: 9 | M9: Unité exacte du prix à confirmer | N9: TARIF
A10: AP-067 | B10: Poste restante | C10: Poste restante — autres objets | D10: Tous publics | E10: Poste restante | F10: 55 DA | G10: 55 | J10: Par objet | K10: Garde maximale annoncée : 1 mois | L10: 9 | M10: Unité exacte du prix à confirmer | N10: TARIF
A11: AP-068 | B11: Poste restante | C11: Abonnement annuel poste restante | D11: Tous publics | E11: Poste restante | F11: 2 000 DA / an | G11: 2000 | J11: Annuelle | K11: Carte d'abonnement valable 1 an | L11: 9 | M11: Confirmer date et tarif sur source officielle | N11: TARIF
A12: AP-069 | B12: Procurations | C12: Procuration postale | D12: Tous publics | E12: Guichet / notaire | F12: Droit de timbre | K12: Modèle 776 ou procuration notariée ; valable uniquement pour l’établissement dépositaire | L12: 9 | M12: Montant droit de timbre et portée juridique à confirmer | N12: TARIF
A13: AP-070 | B13: Télégrammes | C13: Service Barki@tic | D13: Tous publics | E13: Tout bureau / convention entreprise | F13: Non spécifié | K13: Envoi de télégrammes électroniques ; personnes physiques : bureau ; personnes morales : convention avec DUPW | L13: 9 | M13: Clarifier discordance avec mention de Barki@tic pour paiement de factures (§7) | N13: TARIF
A14: AP-071 | B14: Produits à valeur ajoutée | C14: Produits à valeur ajoutée postaux | D14: Tous publics | E14: Bureau de poste | F14: Non spécifié | K14: Vignettes auto, timbres fiscaux/amendes/poste, pages MAGHREB, pochettes philatéliques | L14: 9 | M14: Chaque produit doit avoir son tarif propre si intégré ultérieurement | N14: TARIF
A15: AP-072 | B15: Philatélie | C15: Abonnement philatélique | D15: Tous publics | E15: Recette principale | F15: Abonnement mensuel — montant non indiqué | J15: Mensuelle | K15: Souscription locale, versement mensuel, envoi du timbre du 1er jour par recommandé | L15: 9 | M15: Prix, conditions d’envoi et frais postaux manquants | N15: TARIF
A16: AP-073 | B16: Réclamations | C16: Réclamation courrier recommandé domestique non reçu | D16: Tous publics | E16: Formulaire N°846 | F16: Délai : 1 an | K16: À compter du lendemain de la date de dépôt | L16: 9 | M16: Confirmer date et tarif sur source officielle | N16: DÉLAI
A17: AP-074 | B17: Réclamations | C17: Réclamation courrier recommandé international non reçu | D17: Tous publics | E17: Formulaire CN08 | F17: Délai : 6 mois | K17: À compter du lendemain de la date de dépôt | L17: 9 | M17: Ne pas convertir automatiquement les 6 mois en un nombre fixe de jours | N17: DÉLAI
A18: AP-075 | B18: Codes postaux | C18: Consultation du code postal | D18: Tous publics | E18: www.poste.dz / guichet | F18: Gratuit | G18: 0 | J18: Par consultation | K18: Recherche sur poste.dz ou au bureau de poste de résidence | L18: 9 | M18: Confirmer date et tarif sur source officielle | N18: TARIF

Sheet 06_BaridiMob_ECCP
A1: BARIDIMOB, E-CCP ET SERVICES NUMÉRIQUES
A2: Tarifs de virements et d'abonnements extraits du texte ; barèmes incomplets signalés.
A4: ID | B4: Sous-catégorie | C4: Service / information | D4: Public | E4: Canal | F4: Tarif annoncé | G4: Montant DA | H4: Max DA | I4: % max | J4: Fréquence | K4: Conditions / procédure | L4: Section | M4: Vérification nécessaire | N4: Type
A5: AP-022 | B5: E-CCP | C5: Accès au service CCP en ligne | D5: Particulier | E5: Web / smartphone | F5: Non spécifié | K5: Après inscription et activation ; solde, mouvements, transferts et paiement de factures | L5: 7 | M5: Fonctions et tarification canal à confirmer | N5: TARIF
A6: AP-032 | B6: Virement mobile | C6: Virement CCP via BaridiMob | D6: Particulier | E6: BaridiMob | F6: De 1 000 à 200 000 DA/jour | J6: Par jour | K6: Bénéficiaire peut retirer les fonds le jour même selon texte | L6: 8 | M6: Plafond de 200 000 DA/jour à vérifier ; tarification décrite séparément section 9 | N6: PLAFOND
A7: AP-061 | B7: BaridiMob | C7: Adhésion BaridiMob | D7: Particulier | E7: Application BaridiMob | F7: 50 DA | G7: 50 | J7: À l’adhésion | L7: 9 | M7: Barème canal/applicable à vérifier | N7: TARIF
A8: AP-062 | B8: BaridiMob | C8: Virement via BaridiMob — frais | D8: Particulier | E8: Application BaridiMob | F8: 12 à 24 DA / virement | G8: 12 | H8: 24 | J8: Par virement | K8: Tranches de montant non indiquées dans le texte | L8: 9 | M8: Barème détaillé par tranche à obtenir avant calcul exact | N8: TARIF
A9: AP-063 | B9: BaridiMob | C9: Abonnement mensuel BaridiMob | D9: Particulier | E9: Application BaridiMob | F9: 50 DA / mois | G9: 50 | J9: Mensuelle | L9: 9 | M9: Vérifier caractère automatique/optionnel | N9: TARIF

Sheet 07_Identifiants_WU
A1: RIP / NIP ET TRANSFERT WESTERN UNION ENTRANT
A2: L'identifiant de compte ne doit pas être confondu avec une donnée tarifaire. Western Union désigne ici un paiement entrant en DZD, pas un virement international sortant depuis le CCP.
A4: ID | B4: Famille | C4: Objet | D4: Service / information | E4: Public | F4: Tarif | G4: Description source | H4: Point de contrôle | I4: Section | J4: Nature
A5: AP-017 | B5: International - remise reçue | C5: Transferts reçus | D5: Réception d'un transfert Western Union | E5: Tous publics | F5: Non spécifié | G5: Paiement en DZD ; maximum annoncé 500 000 DA ; pièce d’identité et MTCN obligatoires | H5: Vérifier plafond, disponibilité et nature du transfert : remise entrante seulement | I5: 7 | J5: TARIF
A6: AP-042 | B6: Identifiants et référentiels | C6: RIP | D6: RIP utilisé pour virement GAB | E6: Tous publics | F6: Non applicable | G6: Le numéro RIP est mentionné sur le chèque bleu | I6: 8 | J6: DÉFINITION
A7: AP-043 | B7: Identifiants et référentiels | C7: RIP | D7: Définition RIP | E7: Tous publics | F7: Non applicable | G7: Identifiant du compte postal ; texte cite nom, prénom, adresse, NIP | H7: Vérifier composition normative et présentation exacte du RIP | I7: 8 | J7: DÉFINITION
A8: AP-044 | B8: Identifiants et référentiels | C8: NIP | D8: Définition NIP | E8: Tous publics | F8: Non applicable | G8: Le texte indique code banque 007, code agence 99999, numéro de compte CCP et clé | H8: Contrôler terminologie et structure des identifiants (RIP/NIP) | I8: 8 | J8: DÉFINITION
A9: AP-045 | B9: Identifiants et référentiels | C9: RIP | D9: Utilité du RIP | E9: Tous publics | F9: Non applicable | G9: Coordonnées du compte postal pour GAB, BaridiMob et autres opérations | I9: 8 | J9: DÉFINITION

Sheet 08_Plafonds_Delais
A1: PLAFONDS, DURÉES ET DÉLAIS DE RÉCLAMATION
A2: Comparateur spécifique des limites d'opération et des délais. Aucun délai n'est traité comme un tarif ; les années/mois calendaires restent en unités calendaires.
A4: ID | B4: Famille | C4: Opération | D4: Public | E4: Min opération DA | F4: Max opération DA | G4: Base limite | H4: Réclamation jours | I4: Réclamation mois | J4: Texte source | K4: Conditions | L4: À vérifier
A5: AP-029 | B5: Monétique EDAHABIA | C5: Plafond de retrait sur GAB | D5: Porteur particulier | F5: 50000 | G5: Jour | J5: 50 000 DA/jour
A6: AP-030 | B6: Monétique EDAHABIA | C6: Plafond de paiement TPE | D6: Porteur particulier | F6: 200000 | G6: Jour | J6: 200 000 DA/jour
A7: AP-031 | B7: Monétique EDAHABIA | C7: Virement CCP vers CCP via GAB | D7: Porteur particulier | E7: 1000 | F7: 50000 | G7: Jour | J7: De 1 000 à 50 000 DA/jour | K7: Numéro RIP du bénéficiaire figurant sur le chèque bleu | L7: Frais de virement par GAB non spécifiés
A8: AP-032 | B8: Services numériques | C8: Virement CCP via BaridiMob | D8: Particulier | E8: 1000 | F8: 200000 | G8: Jour | J8: De 1 000 à 200 000 DA/jour | K8: Bénéficiaire peut retirer les fonds le jour même selon texte | L8: Plafond de 200 000 DA/jour à vérifier ; tarification décrite séparément section 9
A9: AP-036 | B9: Monétique EDAHABIA | C9: Réclamation retrait sur GAB Algérie Poste | D9: Porteur particulier | J9: Délai non défini | K9: Recevabilité non précisée dans le texte | L9: Délai et procédure à obtenir
A10: AP-037 | B10: Monétique EDAHABIA | C10: Réclamation retrait sur GAB bancaire | D10: Porteur particulier | H10: 98 | J10: 98 jours | K10: Délai de recevabilité déclaré
A11: AP-038 | B11: Monétique EDAHABIA | C11: Réclamation e-paiement — opérateurs énumérés | D11: Porteur particulier | H11: 45 | J11: 45 jours | K11: ATM Mobilis, Deazy, Caramma Assurance, CNRC, Macirvi, CAAT selon texte | L11: Orthographe/identité exacte des commerçants à confirmer
A12: AP-039 | B12: Monétique EDAHABIA | C12: Réclamation e-paiement Algérie Télécom | D12: Porteur particulier | H12: 90 | J12: 90 jours
A13: AP-040 | B13: Monétique EDAHABIA | C13: Réclamation e-paiement Air Algérie | D13: Porteur particulier | H13: 120 | J13: 120 jours
A14: AP-073 | B14: Réseau et services postaux | C14: Réclamation courrier recommandé domestique non reçu | D14: Tous publics | I14: 12 | J14: Délai : 1 an | K14: À compter du lendemain de la date de dépôt | L14: Délai calendaire d'un an : ne pas assimiler à 365 jours (année bissextile)
A15: AP-074 | B15: Réseau et services postaux | C15: Réclamation courrier recommandé international non reçu | D15: Tous publics | I15: 6 | J15: Délai : 6 mois | K15: À compter du lendemain de la date de dépôt | L15: Ne pas convertir automatiquement les 6 mois en un nombre fixe de jours

Sheet 09_Bareme_PINPAD
A1: BARÈME RETRAIT PIN PAD — DÉCOMPOSITION DES TRANCHES
A2: Tarif retranscrit de la section 8. Aucune formule de tarif total n'est activée : la règle de calcul par tranche et l'arrondi aux 1 000 DA ne sont pas documentés.
A4: Code barème | B4: Composant | C4: Seuil début DA | D4: Seuil fin DA | E4: Valeur | F4: Unité | G4: Texte de la règle | H4: Statut calcul
A5: PINPAD-01 | B5: Frais fixe | E5: 18 | F5: DA / retrait | G5: S'ajoute au tarif variable | H5: Oui — prix fixe communiqué
A6: PINPAD-01 | B6: Tranche annoncée 1 | C6: 0 | D6: 18000 | E6: 2 | F6: DA / 1 000 DA | G6: Jusqu'à 18 000 DA | H6: Interprétation de tranche et arrondi à confirmer
A7: PINPAD-01 | B7: Tranche annoncée 2 | C7: 18000 | D7: 1000000 | E7: 3 | F7: DA / 1 000 DA | G7: De 18 000 à 1 000 000 DA | H7: Progressif marginal ou taux appliqué à tout le montant ?
A8: PINPAD-01 | B8: Tranche annoncée 3 | C8: 1000000 | E8: 6 | F8: DA / 1 000 DA | G8: Au-dessus de 1 000 000 DA | H8: Plafond pratique, arrondi et unité à confirmer

Sheet 10_Matrice_FINCLUDIA
A1: MATRICE D’INTÉGRATION AU COMPARATEUR FINCLUDIA
A2: Cette feuille indique le niveau de couverture, le segment et les limites de comparabilité. Les tarifs non validés doivent rester non publiables.
A4: Famille FINCLUDIA | B4: Public cible | C4: Couverture dans texte | D4: Synthèse / type de donnée | E4: Références catalogue | F4: Précaution d'intégration
A5: Ouverture et gestion de comptes | B5: Particulier | C5: Couvert | D5: Compte CCP ouverture et tenue gratuites, selon données fournies | E5: AP-001, AP-002 | F5: Comparer uniquement le CCP avec comptes de paiement / comptes chèques
A6: Opérations de caisse | B6: Particulier | C6: Couvert | D6: Retrait et versement au guichet gratuits | E6: AP-003, AP-004 | F6: Distinguer guichet des retraits GAB
A7: Virements domestiques | B7: Particulier | C7: Partiel | D7: Virements CCP et GAB / BaridiMob : frais et plafonds mixtes | E7: AP-005, AP-031, AP-032, AP-062 | F7: Barème virement CCP et paliers 12–24 DA non détaillés
A8: Monétique locale (carte) | B8: Particulier | C8: Couvert | D8: EDAHABIA : création, PIN, blocage, retraits GAB, paiements | E8: AP-007 à AP-009; AP-024 à AP-034 | F8: Vérifier durée de validité ; frais renouvellement
A9: Monétique / acquisition TPE | B9: Professionnel / Entreprise | C9: Couvert | D9: Abonnement TPE mobile + commission commerçant | E9: AP-051 à AP-055; AP-058 à AP-060 | F9: Forfait 800 HT, composantes 300+300+200 non additives
A10: Services digitaux | B10: Particulier | C10: Couvert | D10: E-CCP et BaridiMob, adhésion/abonnement/virement | E10: AP-022, AP-032, AP-061 à AP-063 | F10: Vérifier souscription et grille des frais
A11: Épargne et placements | B11: Particulier | C11: Partiel | D11: Produits évoqués, taux et frais non communiqués | E11: AP-013 à AP-016 | F11: Ne pas inventer de rendement ni statut d'offre
A12: Crédits / financements | B12: Tous segments | C12: Non documenté | D12: Aucun produit ni taux de crédit figurant dans le texte fourni | E12: — | F12: Non documenté ne signifie pas 'impossible' ou 'interdit'
A13: Cartes internationales | B13: Tous segments | C13: Non documenté | D13: Aucune grille carte internationale dans le texte | E13: — | F13: Ne pas conclure à une absence universelle de produit
A14: Change / comptes en devises | B14: Tous segments | C14: Non documenté | D14: Aucune grille de change/compte devises; WU paie en DA | E14: AP-017 | F14: Ne pas assimiler Western Union entrant à un virement sortant
A15: Services internationaux reçus | B15: Tous publics | C15: Partiel | D15: Western Union : remise reçue en DZD et maximum annoncé | E15: AP-017 | F15: Plafond/règles WU à valider
... A19: Réclamations et recours | B19: Particulier / Tous publics | C19: Couvert (procédure) | D19: Délai variable selon canal/prestataire | E19: AP-035 à AP-040; AP-073 à AP-074 | F19: Ne pas afficher un délai unique pour toute réclamation

Sheet 11_Controle_Validation
A1: REGISTRE DES POINTS À VÉRIFIER AVANT PUBLICATION
A2: Toutes les conditions sont issues du texte transmis et non de pièces officielles datées. Les contrôles demandés ci-dessous ne constituent pas une vérification réalisée.
A4: ID contrôle | B4: Service / ID | C4: Limite ou anomalie | D4: Preuve attendue | E4: Impact produit
A5: P01 | B5: Tous tarifs | C5: Absence de référence officielle datée et date d'effet | D5: Obtenir grille tarifaire AP à jour et liens par rubrique | E5: Toute publication externe
A6: P02 | B6: AP-009 | C6: Validité EDAHABIA indiquée 2 ans, mention « classique 4 ans » | D6: Valider génération de carte, durée officielle et frais renouvellement | E6: Cotisation annualisée
A7: P03 | B7: AP-026 | C7: PIN PAD : mode de calcul progressif, base, plafond, arrondi des milliers inconnus | D7: Obtenir exemple de calcul certifié pour trois montants frontières | E7: Calcul coût retrait PIN PAD
A8: P04 | B8: AP-031, AP-032 | C8: Plafonds GAB/BaridiMob, unité/jour et éventuelle cumulativité | D8: Valider plafond produit, profil, version et circuit | E8: Affichage plafonds
A9: P05 | B9: AP-005, AP-062 | C9: Frais virement CCP non précisés et BaridiMob 12–24 DA sans tranches | D9: Obtenir barème exhaustif par montant/canal | E9: Comparaison virements
A10: P06 | B10: AP-052, AP-058:060 | C10: 800 DA HT TPE et trois composantes incluses | D10: Valider TVA, facturation, éventuelle caution et montant courant | E10: Coût annuel TPE
A11: P07 | B11: AP-053 | C11: Commission TPE « jusqu'à 1,50% » sans grille des paliers | D11: Obtenir commission effective par segment/montant | E11: Simulation commerçant
A12: P08 | B12: AP-035:040 | C12: Délai réclamation variable selon canal/partenaire | D12: Confirmer base contractuelle, point de départ et partenaires | E12: Parcours réclamations
A13: P09 | B13: AP-013:016 | C13: Épargne/plan logement/investissement évoqués sans produits précis | D13: Obtenir documentation produit avant création offre | E13: Comparateur épargne
A14: P10 | B14: AP-017 | C14: WU réception DA, plafond 500 000 DA ; détails de disponibilité | D14: Confirmer plafond, partenaires et pièces | E14: Services internationaux
A15: P11 | B15: AP-042:045 | C15: Terminologie RIP vs NIP et composants de l'identifiant postal | D15: Valider définitions officielles, exemples masqués et normes | E15: Fiche pédagogique
... A20: P16 | B20: Absence de données | C20: Crédit, carte internationale, devises, coffre non documentés | D20: Ne jamais importer une offre à partir d'une absence de données | E20: Bloquer ces catégories

Sheet 12_Import_FINCLUDIA
A1: EXPORT NORMALISÉ — INTÉGRATION FINCLUDIA
A2: Schéma prêt pour mapping technique. Aucun booléen de publication/calcul n'est activé : absence de pièce officielle datée. Les composantes TPE ont un parent et ne doivent pas être comptées deux fois.
A4: provider_id | B4: provider_name | C4: country_code | D4: service_id | E4: service_family | F4: subfamily | G4: customer_segment | H4: service_name | I4: operation_channel | J4: entry_kind | K4: fee_mode | L4: fee_amount_dzd | M4: fee_amount_max_dzd | N4: fee_rate_max | O4: price_period | P4: limit_min_dzd | Q4: limit_max_dzd | R4: limit_period | S4: complaint_delay_days | T4: complaint_delay_months | U4: calculation_rule_id | V4: parent_fee_id | W4: raw_tariff_text | X4: raw_conditions | Y4: source_section | Z4: source_proof_url | AA4: valid_from | AB4: checked_at | AC4: verification_status | AD4: publishable | AE4: auto_compute | AF4: review_notes
A5: DZ_ALGERIE_POSTE | B5: Algérie Poste | C5: DZ | D5: AP-001 | E5: comptes_et_services_ccp | F5: Comptes | G5: Particulier | H5: Ouverture d’un compte CCP | I5: Guichet | J5: TARIF | K5: GRATUIT_EXPLICITE | L5: 0 | O5: À l’ouverture | W5: Gratuit | X5: Pièce d'identité, formulaire CH1/CH2 ; bureau de poste desservant l'adresse | Y5: 7 | AC5: UNVERIFIED_USER_SUPPLIED | AD5: FALSE | AE5: FALSE | AF5: Vérifier exigences documentaires pour particuliers/professionnels
A6: DZ_ALGERIE_POSTE | B6: Algérie Poste | C6: DZ | D6: AP-002 | E6: comptes_et_services_ccp | F6: Comptes | G6: Particulier | H6: Tenue de compte CCP | I6: Compte CCP | J6: TARIF | K6: GRATUIT_EXPLICITE | L6: 0 | O6: Récurrent | W6: Gratuit | Y6: 7 | AC6: UNVERIFIED_USER_SUPPLIED | AD6: FALSE | AE6: FALSE | AF6: Confirmer conditions et exemptions
A7: DZ_ALGERIE_POSTE | B7: Algérie Poste | C7: DZ | D7: AP-003 | E7: comptes_et_services_ccp | F7: Caisse | G7: Particulier | H7: Retrait d'espèces au guichet CCP | I7: Guichet | J7: TARIF | K7: GRATUIT_EXPLICITE | L7: 0 | O7: Par opération | W7: Gratuit | X7: Pièce d’identité et livret CCP | Y7: 7 | AC7: UNVERIFIED_USER_SUPPLIED | AD7: FALSE | AE7: FALSE | AF7: Obtenir document officiel, date et validation avant diffusion
A8: DZ_ALGERIE_POSTE | B8: Algérie Poste | C8: DZ | D8: AP-004 | E8: comptes_et_services_ccp | F8: Caisse | G8: Particulier | H8: Versement d'espèces au guichet CCP | I8: Guichet | J8: TARIF | K8: GRATUIT_EXPLICITE | L8: 0 | O8: Par opération | W8: Gratuit | X8: Pièce d’identité et livret CCP | Y8: 7 | AC8: UNVERIFIED_USER_SUPPLIED | AD8: FALSE | AE8: FALSE | AF8: Obtenir document officiel, date et validation avant diffusion
A9: DZ_ALGERIE_POSTE | B9: Algérie Poste | C9: DZ | D9: AP-005 | E9: comptes_et_services_ccp | F9: Virements | G9: Particulier | H9: Virement entre comptes CCP | I9: Guichet / électronique | J9: TARIF | K9: NON_CHIFFRÉ | W9: Des frais peuvent s’appliquer | X9: Selon montant et destination | Y9: 7 | AC9: UNVERIFIED_USER_SUPPLIED | AD9: FALSE | AE9: FALSE | AF9: Barème effectif et canal non détaillés
A10: DZ_ALGERIE_POSTE | B10: Algérie Poste | C10: DZ | D10: AP-006 | E10: comptes_et_services_ccp | F10: Paiement de factures | G10: Particulier | H10: Paiement de factures au guichet ou à distance | I10: Guichet / Barki@tic (cité) | J10: TARIF | K10: GRATUIT_EXPLICITE | L10: 0 | O10: Par opération | W10: Gratuit | X10: Présentation de la facture et du livret CCP au guichet | Y10: 7 | AC10: UNVERIFIED_USER_SUPPLIED | AD10: FALSE | AE10: FALSE | AF10: Vérifier le nom du service numérique de paiement des factures ; Barki@tic est aussi décrit comme télégramme
A11: DZ_ALGERIE_POSTE | B11: Algérie Poste | C11: DZ | D11: AP-007 | E11: cartes_monetique_locale | F11: Gestion carte | G11: Porteur particulier | H11: Réédition du code PIN EDAHABIA | I11: Guichet / E-CCP / BaridiMob | J11: TARIF | K11: FIXE_DÉCLARÉ | L11: 200 | O11: Par demande | W11: 200 DA | X11: Sur demande | Y11: 7, 8 | AC11: UNVERIFIED_USER_SUPPLIED | AD11: FALSE | AE11: FALSE | AF11: Obtenir document officiel, date et validation avant diffusion
A12: DZ_ALGERIE_POSTE | B12: Algérie Poste | C12: DZ | D12: AP-008 | E12: cartes_monetique_locale | F12: Gestion carte | G12: Porteur particulier | H12: Blocage ou résiliation de la carte EDAHABIA | I12: Guichet / service | J12: TARIF | K12: FIXE_DÉCLARÉ | L12: 30 | O12: Par opération | W12: 30 DA | Y12: 7, 8 | AC12: UNVERIFIED_USER_SUPPLIED | AD12: FALSE | AE12: FALSE | AF12: Obtenir document officiel, date et validation avant diffusion
A13: DZ_ALGERIE_POSTE | B13: Algérie Poste | C13: DZ | D13: AP-009 | E13: cartes_monetique_locale | F13: Émission carte | G13: Porteur particulier | H13: Création ou renouvellement EDAHABIA | I13: Guichet / renouvellement auto | J13: TARIF | K13: FIXE_DÉCLARÉ | L13: 350 | O13: Par carte / cycle annoncé de 2 ans | W13: 350 DA | X13: Validité annoncée 2 ans ; renouvellement automatique ; comparaison avec carte « classique » 4 ans dans le texte | Y13: 7, 8 | AC13: UNVERIFIED_USER_SUPPLIED | AD13: FALSE | AE13: FALSE | AF13: Valider validité 2 ans vs mention 4 ans et prix exact
A14: DZ_ALGERIE_POSTE | B14: Algérie Poste | C14: DZ | D14: AP-010 | E14: comptes_et_services_ccp | F14: Documents | G14: Particulier | H14: Certificat bancaire CCP | I14: Guichet | J14: TARIF | K14: NON_CHIFFRÉ | W14: Non spécifié | Y14: 7 | AC14: UNVERIFIED_USER_SUPPLIED | AD14: FALSE | AE14: FALSE | AF14: Tarif, pièces et délivrance à documenter
A15: DZ_ALGERIE_POSTE | B15: Algérie Poste | C15: DZ | D15: AP-011 | E15: comptes_et_services_ccp | F15: Documents | G15: Particulier | H15: Relevé de compte CCP | I15: Guichet / E-CCP | J15: TARIF | K15: GRATUIT_EXPLICITE | L15: 0 | O15: Par demande | W15: Gratuit | X15: Au guichet ou en ligne pour les utilisateurs avec accès électronique | Y15: 7 | AC15: UNVERIFIED_USER_SUPPLIED | AD15: FALSE | AE15: FALSE | AF15: Confirmer gratuité selon format et canal
A16: DZ_ALGERIE_POSTE | B16: Algérie Poste | C16: DZ | D16: AP-012 | E16: comptes_et_services_ccp | F16: Chèques | G16: Particulier | H16: Perte ou vol du chéquier CCP | I16: Guichet | J16: PROCÉDURE | K16: NON_TARIFAIRE | W16: Non spécifié | X16: Blocage immédiat et nouveau chéquier après vérification | Y16: 7 | AC16: UNVERIFIED_USER_SUPPLIED | AD16: FALSE | AE16: FALSE | AF16: Vérifier frais de remplacement, délais et opposition
A17: DZ_ALGERIE_POSTE | B17: Algérie Poste | C17: DZ | D17: AP-013 | E17: comptes_et_services_ccp | F17: Épargne | G17: Particulier | H17: Compte épargne postal | I17: Bureau de poste | J17: TARIF | K17: NON_CHIFFRÉ | W17: Non spécifié | X17: Intérêts selon réglementation en vigueur | Y17: 7 | AC17: UNVERIFIED_USER_SUPPLIED | AD17: FALSE | AE17: FALSE | AF17: Vérifier existence, opérateur, taux, conditions et distinction CCP/épargne
A18: DZ_ALGERIE_POSTE | B18: Algérie Poste | C18: DZ | D18: AP-014 | E18: comptes_et_services_ccp | F18: Épargne | G18: Particulier | H18: Plan d’épargne logement | I18: Bureau de poste | J18: TARIF | K18: NON_CHIFFRÉ | W18: Non spécifié | X18: Souscription auprès du bureau de poste | Y18: 7 | AC18: UNVERIFIED_USER_SUPPLIED | AD18: FALSE | AE18: FALSE | AF18: Confirmer l’existence actuelle et modalités ; ne pas assimiler à crédit
A19: DZ_ALGERIE_POSTE | B19: Algérie Poste | C19: DZ | D19: AP-015 | E19: comptes_et_services_ccp | F19: Virements | G19: Particulier | H19: Virement permanent CCP | I19: Guichet / en ligne | J19: TARIF | K19: NON_CHIFFRÉ | W19: Non spécifié | X19: Transfert automatique ; demande avec signature autorisée | Y19: 7 | AC19: UNVERIFIED_USER_SUPPLIED | AD19: FALSE | AE19: FALSE | AF19: Barème, disponibilité et fréquence à confirmer
A20: DZ_ALGERIE_POSTE | B20: Algérie Poste | C20: DZ | D20: AP-016 | E20: comptes_et_services_ccp | F20: Placements | G20: Particulier | H20: Produit d’investissement postal | I20: Bureau de poste | J20: TARIF | K20: NON_CHIFFRÉ | W20: Non spécifié | X20: Formulaire, pièces justificatives et dépôt initial | Y20: 7 | AC20: UNVERIFIED_USER_SUPPLIED | AD20: FALSE | AE20: FALSE | AF20: Produit non identifié précisément : ne pas créer d’offre de placement sans nom/taux
A21: DZ_ALGERIE_POSTE | B21: Algérie Poste | C21: DZ | D21: AP-017 | E21: transfert_recu_international | F21: Transferts reçus | G21: Tous publics | H21: Réception d'un transfert Western Union | I21: Guichet | J21: TARIF | K21: NON_CHIFFRÉ | W21: Non spécifié | X21: Paiement en DZD ; maximum annoncé 500 000 DA ; pièce d’identité et MTCN obligatoires | Y21: 7 | AC21: UNVERIFIED_USER_SUPPLIED | AD21: FALSE | AE21: FALSE | AF21: Vérifier plafond, disponibilité et nature du transfert : remise entrante seulement
A22: DZ_ALGERIE_POSTE | B22: Algérie Poste | C22: DZ | D22: AP-018 | E22: comptes_et_services_ccp | F22: Paiements pour tiers | G22: Tous publics | H22: Paiement de prestations/factures pour tiers | I22: Guichet | J22: TARIF | K22: GRATUIT_EXPLICITE | L22: 0 | O22: Par paiement | W22: Gratuit | X22: Téléphone, eau, électricité, SONELGAZ, BNP, ONEFD, EMS, TLS Contact, AFS, etc. | Y22: 7 | AC22: UNVERIFIED_USER_SUPPLIED | AD22: FALSE | AE22: FALSE | AF22: Vérifier éventuelles exceptions par partenaire
A23: DZ_ALGERIE_POSTE | B23: Algérie Poste | C23: DZ | D23: AP-019 | E23: comptes_et_services_ccp | F23: Recharges | G23: Tous publics | H23: Recharge téléphonique | I23: Guichet / PDV | J23: TARIF | K23: NON_CHIFFRÉ | W23: Non spécifié | X23: Ooredoo, Djezzy, Mobilis, Assel ; Mobilis MASTER uniquement pour PDV | Y23: 7 | AC23: UNVERIFIED_USER_SUPPLIED | AD23: FALSE | AE23: FALSE | AF23: Vérifier noms des opérateurs, restrictions et frais
A24: DZ_ALGERIE_POSTE | B24: Algérie Poste | C24: DZ | D24: AP-020 | E24: comptes_et_services_ccp | F24: Comptes | G24: Particulier | H24: Clôture de compte CCP | I24: Bureau de domiciliation | J24: TARIF | K24: GRATUIT_EXPLICITE | L24: 0 | O24: Par clôture | W24: Gratuit | X24: Pièce d'identité, formulaire de clôture ; restitution du solde | Y24: 7 | AC24: UNVERIFIED_USER_SUPPLIED | AD24: FALSE | AE24: FALSE | AF24: Obtenir document officiel, date et validation avant diffusion
A25: DZ_ALGERIE_POSTE | B25: Algérie Poste | C25: DZ | D25: AP-021 | E25: comptes_et_services_ccp | F25: Documents | G25: Particulier | H25: Renouvellement carte CCP ou livret | I25: Guichet | J25: TARIF | K25: NON_CHIFFRÉ | W25: Des frais peuvent s’appliquer | X25: Ancien livret/carte et pièce d’identité | Y25: 7 | AC25: UNVERIFIED_USER_SUPPLIED | AD25: FALSE | AE25: FALSE | AF25: Produit de référence et tarif à préciser ; distinguer EDAHABIA
A26: DZ_ALGERIE_POSTE | B26: Algérie Poste | C26: DZ | D26: AP-022 | E26: banque_distance | F26: E-CCP | G26: Particulier | H26: Accès au service CCP en ligne | I26: Web / smartphone | J26: TARIF | K26: NON_CHIFFRÉ | W26: Non spécifié | X26: Après inscription et activation ; solde, mouvements, transferts et paiement de factures | Y26: 7 | AC26: UNVERIFIED_USER_SUPPLIED | AD26: FALSE | AE26: FALSE | AF26: Fonctions et tarification canal à confirmer
A27: DZ_ALGERIE_POSTE | B27: Algérie Poste | C27: DZ | D27: AP-023 | E27: comptes_et_services_ccp | F27: Réclamations | G27: Particulier | H27: Contester une opération CCP | I27: Bureau de poste | J27: PROCÉDURE | K27: NON_TARIFAIRE | W27: Non spécifié | X27: Se rapprocher du bureau de poste | Y27: 7 | AC27: UNVERIFIED_USER_SUPPLIED | AD27: FALSE | AE27: FALSE | AF27: Délai et pièces à préciser
A28: DZ_ALGERIE_POSTE | B28: Algérie Poste | C28: DZ | D28: AP-024 | E28: cartes_monetique_locale | F28: Retrait carte | G28: Porteur particulier | H28: Retrait GAB Algérie Poste | I28: GAB Algérie Poste | J28: TARIF | K28: FIXE_DÉCLARÉ | L28: 30 | O28: Par retrait | W28: 30 DA | Y28: 8 | AC28: UNVERIFIED_USER_SUPPLIED | AD28: FALSE | AE28: FALSE | AF28: Obtenir document officiel, date et validation avant diffusion
A29: DZ_ALGERIE_POSTE | B29: Algérie Poste | C29: DZ | D29: AP-025 | E29: cartes_monetique_locale | F29: Retrait carte | G29: Porteur particulier | H29: Retrait GAB d'une banque | I29: GAB bancaire interbancaire | J29: TARIF | K29: FIXE_DÉCLARÉ | L29: 35 | O29: Par retrait | W29: 35 DA | Y29: 8 | AC29: UNVERIFIED_USER_SUPPLIED | AD29: FALSE | AE29: FALSE | AF29: Obtenir document officiel, date et validation avant diffusion
A30: DZ_ALGERIE_POSTE | B30: Algérie Poste | C30: DZ | D30: AP-026 | E30: cartes_monetique_locale | F30: Retrait PIN PAD | G30: Porteur particulier | H30: Retrait sur PIN PAD | I30: PIN PAD | J30: TARIF | K30: BARÈME_VARIABLE_INCOMPLET | L30: 18 | O30: Par retrait | U30: PINPAD-01 | W30: 18 DA + barème progressif annoncé | X30: 18 DA fixe + 2 DA par 1 000 jusqu'à 18 000 ; 3 DA par 1 000 jusqu'à 1 000 000 ; 6 DA par 1 000 au-dessus. | Y30: 8 | AC30: UNVERIFIED_USER_SUPPLIED | AD30: FALSE | AE30: FALSE | AF30: Calcul marginal/par tranche et arrondi des fractions de 1 000 non spécifiés ; simulation bloquée
A31: DZ_ALGERIE_POSTE | B31: Algérie Poste | C31: DZ | D31: AP-027 | E31: cartes_monetique_locale | F31: Paiement carte | G31: Porteur particulier | H31: Paiement TPE avec EDAHABIA | I31: TPE | J31: TARIF | K31: GRATUIT_EXPLICITE | L31: 0 | O31: Par paiement | W31: Gratuit pour le porteur | X31: Commission supportée par le commerçant | Y31: 8 | AC31: UNVERIFIED_USER_SUPPLIED | AD31: FALSE | AE31: FALSE | AF31: Vérifier périmètre de gratuité porteur
A32: DZ_ALGERIE_POSTE | B32: Algérie Poste | C32: DZ | D32: AP-028 | E32: cartes_monetique_locale | F32: Paiement carte | G32: Porteur particulier | H32: Paiement en ligne EDAHABIA | I32: E-commerce | J32: TARIF | K32: GRATUIT_EXPLICITE | L32: 0 | O32: Par paiement | W32: Gratuit pour le porteur | X32: Commission supportée par l’e-fournisseur | Y32: 8 | AC32: UNVERIFIED_USER_SUPPLIED | AD32: FALSE | AE32: FALSE | AF32: Obtenir document officiel, date et validation avant diffusion
A33: DZ_ALGERIE_POSTE | B33: Algérie Poste | C33: DZ | D33: AP-029 | E33: cartes_monetique_locale | F33: Plafonds carte | G33: Porteur particulier | H33: Plafond de retrait sur GAB | I33: GAB | J33: PLAFOND | K33: NON_TARIFAIRE | O33: Par jour | Q33: 50000 | R33: Jour | W33: 50 000 DA/jour | Y33: 8 | AC33: UNVERIFIED_USER_SUPPLIED | AD33: FALSE | AE33: FALSE | AF33: Obtenir document officiel, date et validation avant diffusion
A34: DZ_ALGERIE_POSTE | B34: Algérie Poste | C34: DZ | D34: AP-030 | E34: cartes_monetique_locale | F34: Plafonds carte | G34: Porteur particulier | H34: Plafond de paiement TPE | I34: TPE | J34: PLAFOND | K34: NON_TARIFAIRE | O34: Par jour | Q34: 200000 | R34: Jour | W34: 200 000 DA/jour | Y34: 8 | AC34: UNVERIFIED_USER_SUPPLIED | AD34: FALSE | AE34: FALSE | AF34: Obtenir document officiel, date et validation avant diffusion
A35: DZ_ALGERIE_POSTE | B35: Algérie Poste | C35: DZ | D35: AP-031 | E35: cartes_monetique_locale | F35: Virement carte | G35: Porteur particulier | H35: Virement CCP vers CCP via GAB | I35: GAB | J35: PLAFOND | K35: NON_TARIFAIRE | O35: Par jour | P35: 1000 | Q35: 50000 | R35: Jour | W35: De 1 000 à 50 000 DA/jour | X35: Numéro RIP du bénéficiaire figurant sur le chèque bleu | Y35: 8 | AC35: UNVERIFIED_USER_SUPPLIED | AD35: FALSE | AE35: FALSE | AF35: Frais de virement par GAB non spécifiés
A36: DZ_ALGERIE_POSTE | B36: Algérie Poste | C36: DZ | D36: AP-032 | E36: banque_distance | F36: Virement mobile | G36: Particulier | H36: Virement CCP via BaridiMob | I36: BaridiMob | J36: PLAFOND | K36: NON_TARIFAIRE | O36: Par jour | P36: 1000 | Q36: 200000 | R36: Jour | W36: De 1 000 à 200 000 DA/jour | X36: Bénéficiaire peut retirer les fonds le jour même selon texte | Y36: 8 | AC36: UNVERIFIED_USER_SUPPLIED | AD36: FALSE | AE36: FALSE | AF36: Plafond de 200 000 DA/jour à vérifier ; tarification décrite séparément section 9
A37: DZ_ALGERIE_POSTE | B37: Algérie Poste | C37: DZ | D37: AP-033 | E37: cartes_monetique_locale | F37: Information transaction | G37: Porteur particulier | H37: Confirmation paiement en ligne | I37: Site + SMS | J37: INFORMATION | K37: NON_TARIFAIRE | W37: Non spécifié | X37: Reçu sur le site et SMS | Y37: 8 | AC37: UNVERIFIED_USER_SUPPLIED | AD37: FALSE | AE37: FALSE | AF37: Obtenir document officiel, date et validation avant diffusion
A38: DZ_ALGERIE_POSTE | B38: Algérie Poste | C38: DZ | D38: AP-034 | E38: cartes_monetique_locale | F38: Information transaction | G38: Porteur particulier | H38: Confirmation paiement TPE | I38: TPE + SMS | J38: INFORMATION | K38: NON_TARIFAIRE | W38: Non spécifié | X38: Ticket de paiement et SMS | Y38: 8 | AC38: UNVERIFIED_USER_SUPPLIED | AD38: FALSE | AE38: FALSE | AF38: Obtenir document officiel, date et validation avant diffusion
A39: DZ_ALGERIE_POSTE | B39: Algérie Poste | C39: DZ | D39: AP-035 | E39: cartes_monetique_locale | F39: Réclamations | G39: Porteur particulier | H39: Réclamation e-paiement | I39: Fournisseur e-commerce | J39: PROCÉDURE | K39: NON_TARIFAIRE | W39: Non spécifié | X39: Contacter e-fournisseur muni d’un ticket ou reçu | Y39: 8 | AC39: UNVERIFIED_USER_SUPPLIED | AD39: FALSE | AE39: FALSE | AF39: Obtenir document officiel, date et validation avant diffusion
A40: DZ_ALGERIE_POSTE | B40: Algérie Poste | C40: DZ | D40: AP-036 | E40: cartes_monetique_locale | F40: Réclamations | G40: Porteur particulier | H40: Réclamation retrait sur GAB Algérie Poste | I40: GAB Algérie Poste | J40: DÉLAI | K40: NON_TARIFAIRE | W40: Délai non défini | X40: Recevabilité non précisée dans le texte | Y40: 8 | AC40: UNVERIFIED_USER_SUPPLIED | AD40: FALSE | AE40: FALSE | AF40: Délai et procédure à obtenir
A41: DZ_ALGERIE_POSTE | B41: Algérie Poste | C41: DZ | D41: AP-037 | E41: cartes_monetique_locale | F41: Réclamations | G41: Porteur particulier | H41: Réclamation retrait sur GAB bancaire | I41: GAB banque | J41: DÉLAI | K41: NON_TARIFAIRE | S41: 98 | W41: 98 jours | X41: Délai de recevabilité déclaré | Y41: 8 | AC41: UNVERIFIED_USER_SUPPLIED | AD41: FALSE | AE41: FALSE | AF41: Obtenir document officiel, date et validation avant diffusion
A42: DZ_ALGERIE_POSTE | B42: Algérie Poste | C42: DZ | D42: AP-038 | E42: cartes_monetique_locale | F42: Réclamations | G42: Porteur particulier | H42: Réclamation e-paiement — opérateurs énumérés | I42: E-commerce | J42: DÉLAI | K42: NON_TARIFAIRE | S42: 45 | W42: 45 jours | X42: ATM Mobilis, Deazy, Caramma Assurance, CNRC, Macirvi, CAAT selon texte | Y42: 8 | AC42: UNVERIFIED_USER_SUPPLIED | AD42: FALSE | AE42: FALSE | AF42: Orthographe/identité exacte des commerçants à confirmer
A43: DZ_ALGERIE_POSTE | B43: Algérie Poste | C43: DZ | D43: AP-039 | E43: cartes_monetique_locale | F43: Réclamations | G43: Porteur particulier | H43: Réclamation e-paiement Algérie Télécom | I43: E-commerce | J43: DÉLAI | K43: NON_TARIFAIRE | S43: 90 | W43: 90 jours | Y43: 8 | AC43: UNVERIFIED_USER_SUPPLIED | AD43: FALSE | AE43: FALSE | AF43: Obtenir document officiel, date et validation avant diffusion
A44: DZ_ALGERIE_POSTE | B44: Algérie Poste | C44: DZ | D44: AP-040 | E44: cartes_monetique_locale | F44: Réclamations | G44: Porteur particulier | H44: Réclamation e-paiement Air Algérie | I44: E-commerce | J44: DÉLAI | K44: NON_TARIFAIRE | S44: 120 | W44: 120 jours | Y44: 8 | AC44: UNVERIFIED_USER_SUPPLIED | AD44: FALSE | AE44: FALSE | AF44: Obtenir document officiel, date et validation avant diffusion
A45: DZ_ALGERIE_POSTE | B45: Algérie Poste | C45: DZ | D45: AP-041 | E45: cartes_monetique_locale | F45: Réseaux | G45: Porteur particulier | H45: Utilisation EDAHABIA sur GAB de banques | I45: Interbancaire | J45: INFORMATION | K45: NON_TARIFAIRE | W45: Non spécifié | X45: Utilisation interbancaire | Y45: 8 | AC45: UNVERIFIED_USER_SUPPLIED | AD45: FALSE | AE45: FALSE | AF45: Accès selon réseau et compatibilité
A46: DZ_ALGERIE_POSTE | B46: Algérie Poste | C46: DZ | D46: AP-042 | E46: donnees_referentielles | F46: RIP | G46: Tous publics | H46: RIP utilisé pour virement GAB | I46: GAB / chèque bleu | J46: DÉFINITION | K46: NON_TARIFAIRE | W46: Non applicable | X46: Le numéro RIP est mentionné sur le chèque bleu | Y46: 8 | AC46: UNVERIFIED_USER_SUPPLIED | AD46: FALSE | AE46: FALSE | AF46: Obtenir document officiel, date et validation avant diffusion
A47: DZ_ALGERIE_POSTE | B47: Algérie Poste | C47: DZ | D47: AP-043 | E47: donnees_referentielles | F47: RIP | G47: Tous publics | H47: Définition RIP | I47: Compte CCP | J47: DÉFINITION | K47: NON_TARIFAIRE | W47: Non applicable | X47: Identifiant du compte postal ; texte cite nom, prénom, adresse, NIP | Y47: 8 | AC47: UNVERIFIED_USER_SUPPLIED | AD47: FALSE | AE47: FALSE | AF47: Vérifier composition normative et présentation exacte du RIP
A48: DZ_ALGERIE_POSTE | B48: Algérie Poste | C48: DZ | D48: AP-044 | E48: donnees_referentielles | F48: NIP | G48: Tous publics | H48: Définition NIP | I48: Compte CCP | J48: DÉFINITION | K48: NON_TARIFAIRE | W48: Non applicable | X48: Le texte indique code banque 007, code agence 99999, numéro de compte CCP et clé | Y48: 8 | AC48: UNVERIFIED_USER_SUPPLIED | AD48: FALSE | AE48: FALSE | AF48: Contrôler terminologie et structure des identifiants (RIP/NIP)
A49: DZ_ALGERIE_POSTE | B49: Algérie Poste | C49: DZ | D49: AP-045 | E49: donnees_referentielles | F49: RIP | G49: Tous publics | H49: Utilité du RIP | I49: Virements / interbancaire | J49: DÉFINITION | K49: NON_TARIFAIRE | W49: Non applicable | X49: Coordonnées du compte postal pour GAB, BaridiMob et autres opérations | Y49: 8 | AC49: UNVERIFIED_USER_SUPPLIED | AD49: FALSE | AE49: FALSE | AF49: Obtenir document officiel, date et validation avant diffusion
A50: DZ_ALGERIE_POSTE | B50: Algérie Poste | C50: DZ | D50: AP-046 | E50: cartes_monetique_locale | F50: Paiement factures | G50: Porteur particulier | H50: Paiement de factures avec EDAHABIA | I50: Carte / services conventionnés | J50: INFORMATION | K50: NON_TARIFAIRE | W50: Non spécifié | X50: Factures d’opérateurs conventionnés listés sur le site Algérie Poste | Y50: 8 | AC50: UNVERIFIED_USER_SUPPLIED | AD50: FALSE | AE50: FALSE | AF50: Liste fournisseurs et éventuels frais à confirmer
A51: DZ_ALGERIE_POSTE | B51: Algérie Poste | C51: DZ | D51: AP-047 | E51: cartes_monetique_locale | F51: Suivi des opérations | G51: Porteur particulier | H51: Relevé opérations carte à la poste | I51: Guichet | J51: INFORMATION | K51: NON_TARIFAIRE | W51: Non spécifié | X51: Relevé pour la période souhaitée | Y51: 8 | AC51: UNVERIFIED_USER_SUPPLIED | AD51: FALSE | AE51: FALSE | AF51: Obtenir document officiel, date et validation avant diffusion
A52: DZ_ALGERIE_POSTE | B52: Algérie Poste | C52: DZ | D52: AP-048 | E52: cartes_monetique_locale | F52: Suivi des opérations | G52: Porteur particulier | H52: Mini-relevé de carte | I52: Réseau GAB bancaire | J52: INFORMATION | K52: NON_TARIFAIRE | W52: Non spécifié | X52: Dix dernières transactions | Y52: 8 | AC52: UNVERIFIED_USER_SUPPLIED | AD52: FALSE | AE52: FALSE | AF52: Obtenir document officiel, date et validation avant diffusion
A53: DZ_ALGERIE_POSTE | B53: Algérie Poste | C53: DZ | D53: AP-049 | E53: cartes_monetique_locale | F53: Suivi des opérations | G53: Porteur particulier | H53: Relevé complet de carte | I53: Site Algérie Poste / E-CCP | J53: INFORMATION | K53: NON_TARIFAIRE | W53: Non spécifié | X53: Relevé complet accessible en ligne selon le texte | Y53: 8 | AC53: UNVERIFIED_USER_SUPPLIED | AD53: FALSE | AE53: FALSE | AF53: Obtenir document officiel, date et validation avant diffusion
A54: DZ_ALGERIE_POSTE | B54: Algérie Poste | C54: DZ | D54: AP-050 | E54: cartes_monetique_locale | F54: Incidents carte | G54: Porteur particulier | H54: Carte oubliée dans un GAB | I54: GAB | J54: PROCÉDURE | K54: NON_TARIFAIRE | W54: Non spécifié | X54: Carte capturée par l’automate ; contacter l’établissement postal pour la récupérer | Y54: 8 | AC54: UNVERIFIED_USER_SUPPLIED | AD54: FALSE | AE54: FALSE | AF54: Obtenir document officiel, date et validation avant diffusion
A55: DZ_ALGERIE_POSTE | B55: Algérie Poste | C55: DZ | D55: AP-051 | E55: tpe_commercant | F55: Équipement TPE | G55: Professionnel / Entreprise | H55: Acquisition / mise à disposition du TPE mobile | I55: TPE mobile | J55: TARIF | K55: GRATUIT_EXPLICITE | L55: 0 | O55: À la mise à disposition | W55: Gratuit | X55: Abonnement mensuel distinct de 800 DA HT | Y55: 8, 9 | AC55: UNVERIFIED_USER_SUPPLIED | AD55: FALSE | AE55: FALSE | AF55: Vérifier gratuité de matériel, dépôt de garantie et modalités d’installation
A56: DZ_ALGERIE_POSTE | B56: Algérie Poste | C56: DZ | D56: AP-052 | E56: tpe_commercant | F56: Abonnement TPE | G56: Professionnel / Entreprise | H56: Abonnement TPE mobile | I56: TPE mobile | J56: TARIF | K56: FIXE_DÉCLARÉ | L56: 800 | O56: Mensuelle | W56: 800 DA HT / mois | X56: 300 DA gestion + 300 DA connectivité + 200 DA adhésion Algérie Poste | Y56: 8, 9 | AC56: UNVERIFIED_USER_SUPPLIED | AD56: FALSE | AE56: FALSE | AF56: Confirmer base HT et éventuel assujettissement TVA
A57: DZ_ALGERIE_POSTE | B57: Algérie Poste | C57: DZ | D57: AP-053 | E57: tpe_commercant | F57: Frais commerçant | G57: Professionnel / Entreprise | H57: Commission transaction sur TPE | I57: TPE | J57: TARIF | K57: TAUX_MAX_NON_EXACT | N57: 0.015 | O57: Par transaction | W57: Jusqu’à 1,50 % du montant | X57: Taux exact selon barème non communiqué | Y57: 8, 9 | AC57: UNVERIFIED_USER_SUPPLIED | AD57: FALSE | AE57: FALSE | AF57: Plafond uniquement, pas de taux fixe exploitable pour tous
A58: DZ_ALGERIE_POSTE | B58: Algérie Poste | C58: DZ | D58: AP-054 | E58: tpe_commercant | F58: Administration TPE | G58: Professionnel / Entreprise | H58: Déménagement / modification adresse TPE | I58: Courrier DUPW | J58: TARIF | K58: GRATUIT_EXPLICITE | L58: 0 | O58: Par demande | W58: Gratuit | X58: Courrier à la Direction d’Unité Postale de Wilaya : ancienne et nouvelle adresse, nouveau numéro de téléphone | Y58: 8, 9 | AC58: UNVERIFIED_USER_SUPPLIED | AD58: FALSE | AE58: FALSE | AF58: Obtenir document officiel, date et validation avant diffusion
A59: DZ_ALGERIE_POSTE | B59: Algérie Poste | C59: DZ | D59: AP-055 | E59: tpe_commercant | F59: Fonctions TPE | G59: Professionnel / Entreprise | H59: Fonctions réalisables sur un TPE | I59: TPE | J59: INFORMATION | K59: NON_TARIFAIRE | W59: Non spécifié | X59: Vente, annulation, remboursement, cash advance | Y59: 8 | AC59: UNVERIFIED_USER_SUPPLIED | AD59: FALSE | AE59: FALSE | AF59: Confirmer disponibilité du cash advance et de chaque fonctionnalité TPE
A60: DZ_ALGERIE_POSTE | B60: Algérie Poste | C60: DZ | D60: AP-056 | E60: services_postaux | F60: Boîtes postales | G60: Particulier | H60: Abonnement boîte postale — personne physique | I60: Bureau de poste | J60: TARIF | K60: FIXE_DÉCLARÉ | L60: 1000 | O60: Annuelle | W60: 1 000 DA / an | X60: Tacite reconduction ; renouvellement à partir du 15 décembre | Y60: 9 | AC60: UNVERIFIED_USER_SUPPLIED | AD60: FALSE | AE60: FALSE | AF60: Obtenir document officiel, date et validation avant diffusion
A61: DZ_ALGERIE_POSTE | B61: Algérie Poste | C61: DZ | D61: AP-057 | E61: services_postaux | F61: Boîtes postales | G61: Professionnel / Entreprise | H61: Abonnement boîte postale — personne morale | I61: Bureau de poste | J61: TARIF | K61: FIXE_DÉCLARÉ | L61: 4200 | O61: Annuelle | W61: 4 200 DA / an | X61: Tacite reconduction ; renouvellement à partir du 15 décembre | Y61: 9 | AC61: UNVERIFIED_USER_SUPPLIED | AD61: FALSE | AE61: FALSE | AF61: Obtenir document officiel, date et validation avant diffusion
A62: DZ_ALGERIE_POSTE | B62: Algérie Poste | C62: DZ | D62: AP-058 | E62: tpe_commercant | F62: Détail abonnement | G62: Professionnel / Entreprise | H62: Composante abonnement TPE — gestion | I62: TPE mobile | J62: TARIF | K62: COMPOSANTE_INCLUSE_NON_ADDITIVE | L62: 300 | O62: Mensuelle | V62: AP-052 | W62: 300 DA HT / mois | X62: Composante du forfait TPE à 800 DA HT/mois : ne pas additionner si forfait retenu | Y62: 9 | AC62: UNVERIFIED_USER_SUPPLIED | AD62: FALSE | AE62: FALSE | AF62: Inclus dans 800 DA HT mensuels
A63: DZ_ALGERIE_POSTE | B63: Algérie Poste | C63: DZ | D63: AP-059 | E63: tpe_commercant | F63: Détail abonnement | G63: Professionnel / Entreprise | H63: Composante abonnement TPE — connectivité | I63: TPE mobile | J63: TARIF | K63: COMPOSANTE_INCLUSE_NON_ADDITIVE | L63: 300 | O63: Mensuelle | V63: AP-052 | W63: 300 DA HT / mois | X63: Composante du forfait TPE à 800 DA HT/mois : ne pas additionner si forfait retenu | Y63: 9 | AC63: UNVERIFIED_USER_SUPPLIED | AD63: FALSE | AE63: FALSE | AF63: Inclus dans 800 DA HT mensuels
A64: DZ_ALGERIE_POSTE | B64: Algérie Poste | C64: DZ | D64: AP-060 | E64: tpe_commercant | F64: Détail abonnement | G64: Professionnel / Entreprise | H64: Composante abonnement TPE — adhésion Algérie Poste | I64: TPE mobile | J64: TARIF | K64: COMPOSANTE_INCLUSE_NON_ADDITIVE | L64: 200 | O64: Mensuelle | V64: AP-052 | W64: 200 DA HT / mois | X64: Composante du forfait TPE à 800 DA HT/mois : ne pas additionner si forfait retenu | Y64: 9 | AC64: UNVERIFIED_USER_SUPPLIED | AD64: FALSE | AE64: FALSE | AF64: Inclus dans 800 DA HT mensuels
A65: DZ_ALGERIE_POSTE | B65: Algérie Poste | C65: DZ | D65: AP-061 | E65: banque_distance | F65: BaridiMob | G65: Particulier | H65: Adhésion BaridiMob | I65: Application BaridiMob | J65: TARIF | K65: FIXE_DÉCLARÉ | L65: 50 | O65: À l’adhésion | W65: 50 DA | Y65: 9 | AC65: UNVERIFIED_USER_SUPPLIED | AD65: FALSE | AE65: FALSE | AF65: Barème canal/applicable à vérifier
A66: DZ_ALGERIE_POSTE | B66: Algérie Poste | C66: DZ | D66: AP-062 | E66: banque_distance | F66: BaridiMob | G66: Particulier | H66: Virement via BaridiMob — frais | I66: Application BaridiMob | J66: TARIF | K66: FOURCHETTE_INCOMPLÈTE | L66: 12 | M66: 24 | O66: Par virement | W66: 12 à 24 DA / virement | X66: Tranches de montant non indiquées dans le texte | Y66: 9 | AC66: UNVERIFIED_USER_SUPPLIED | AD66: FALSE | AE66: FALSE | AF66: Barème détaillé par tranche à obtenir avant calcul exact
A67: DZ_ALGERIE_POSTE | B67: Algérie Poste | C67: DZ | D67: AP-063 | E67: banque_distance | F67: BaridiMob | G67: Particulier | H67: Abonnement mensuel BaridiMob | I67: Application BaridiMob | J67: TARIF | K67: FIXE_DÉCLARÉ | L67: 50 | O67: Mensuelle | W67: 50 DA / mois | Y67: 9 | AC67: UNVERIFIED_USER_SUPPLIED | AD67: FALSE | AE67: FALSE | AF67: Vérifier caractère automatique/optionnel
A68: DZ_ALGERIE_POSTE | B68: Algérie Poste | C68: DZ | D68: AP-064 | E68: services_postaux | F68: Réexpédition courrier | G68: Tous publics | H68: Réexpédition de courrier — temporaire | I68: Bureau de poste | J68: PROCÉDURE | K68: NON_TARIFAIRE | W68: Non spécifié | X68: Modèle 755A ; changement temporaire indiqué 3 mois ; prolongations payantes possibles | Y68: 9 | AC68: UNVERIFIED_USER_SUPPLIED | AD68: FALSE | AE68: FALSE | AF68: Tarif exact et règles de prolongation non fournis
A69: DZ_ALGERIE_POSTE | B69: Algérie Poste | C69: DZ | D69: AP-065 | E69: services_postaux | F69: Réexpédition courrier | G69: Tous publics | H69: Réexpédition de courrier — définitive | I69: Bureau de poste | J69: PROCÉDURE | K69: NON_TARIFAIRE | W69: Non spécifié | X69: Modèle 755B ; durée indiquée 1 an ; prolongations payantes possibles | Y69: 9 | AC69: UNVERIFIED_USER_SUPPLIED | AD69: FALSE | AE69: FALSE | AF69: Durées (« poste restante » dans le texte) et tarif à confirmer
A70: DZ_ALGERIE_POSTE | B70: Algérie Poste | C70: DZ | D70: AP-066 | E70: services_postaux | F70: Poste restante | G70: Tous publics | H70: Poste restante — journaux | I70: Poste restante | J70: TARIF | K70: FIXE_DÉCLARÉ | L70: 30 | O70: Par objet | W70: 30 DA | X70: Garde maximale annoncée : 1 mois | Y70: 9 | AC70: UNVERIFIED_USER_SUPPLIED | AD70: FALSE | AE70: FALSE | AF70: Unité exacte du prix à confirmer
A71: DZ_ALGERIE_POSTE | B71: Algérie Poste | C71: DZ | D71: AP-067 | E71: services_postaux | F71: Poste restante | G71: Tous publics | H71: Poste restante — autres objets | I71: Poste restante | J71: TARIF | K71: FIXE_DÉCLARÉ | L71: 55 | O71: Par objet | W71: 55 DA | X71: Garde maximale annoncée : 1 mois | Y71: 9 | AC71: UNVERIFIED_USER_SUPPLIED | AD71: FALSE | AE71: FALSE | AF71: Unité exacte du prix à confirmer
A72: DZ_ALGERIE_POSTE | B72: Algérie Poste | C72: DZ | D72: AP-068 | E72: services_postaux | F72: Poste restante | G72: Tous publics | H72: Abonnement annuel poste restante | I72: Poste restante | J72: TARIF | K72: FIXE_DÉCLARÉ | L72: 2000 | O72: Annuelle | W72: 2 000 DA / an | X72: Carte d'abonnement valable 1 an | Y72: 9 | AC72: UNVERIFIED_USER_SUPPLIED | AD72: FALSE | AE72: FALSE | AF72: Obtenir document officiel, date et validation avant diffusion
A73: DZ_ALGERIE_POSTE | B73: Algérie Poste | C73: DZ | D73: AP-069 | E73: services_postaux | F73: Procurations | G73: Tous publics | H73: Procuration postale | I73: Guichet / notaire | J73: TARIF | K73: NON_CHIFFRÉ | W73: Droit de timbre | X73: Modèle 776 ou procuration notariée ; valable uniquement pour l’établissement dépositaire | Y73: 9 | AC73: UNVERIFIED_USER_SUPPLIED | AD73: FALSE | AE73: FALSE | AF73: Montant droit de timbre et portée juridique à confirmer
A74: DZ_ALGERIE_POSTE | B74: Algérie Poste | C74: DZ | D74: AP-070 | E74: services_postaux | F74: Télégrammes | G74: Tous publics | H74: Service Barki@tic | I74: Tout bureau / convention entreprise | J74: TARIF | K74: NON_CHIFFRÉ | W74: Non spécifié | X74: Envoi de télégrammes électroniques ; personnes physiques : bureau ; personnes morales : convention avec DUPW | Y74: 9 | AC74: UNVERIFIED_USER_SUPPLIED | AD74: FALSE | AE74: FALSE | AF74: Clarifier discordance avec mention de Barki@tic pour paiement de factures (§7)
A75: DZ_ALGERIE_POSTE | B75: Algérie Poste | C75: DZ | D75: AP-071 | E75: services_postaux | F75: Produits à valeur ajoutée | G75: Tous publics | H75: Produits à valeur ajoutée postaux | I75: Bureau de poste | J75: TARIF | K75: NON_CHIFFRÉ | W75: Non spécifié | X75: Vignettes auto, timbres fiscaux/amendes/poste, pages MAGHREB, pochettes philatéliques | Y75: 9 | AC75: UNVERIFIED_USER_SUPPLIED | AD75: FALSE | AE75: FALSE | AF75: Chaque produit doit avoir son tarif propre si intégré ultérieurement
A76: DZ_ALGERIE_POSTE | B76: Algérie Poste | C76: DZ | D76: AP-072 | E76: services_postaux | F76: Philatélie | G76: Tous publics | H76: Abonnement philatélique | I76: Recette principale | J76: TARIF | K76: NON_CHIFFRÉ | O76: Mensuelle | W76: Abonnement mensuel — montant non indiqué | X76: Souscription locale, versement mensuel, envoi du timbre du 1er jour par recommandé | Y76: 9 | AC76: UNVERIFIED_USER_SUPPLIED | AD76: FALSE | AE76: FALSE | AF76: Prix, conditions d’envoi et frais postaux manquants
A77: DZ_ALGERIE_POSTE | B77: Algérie Poste | C77: DZ | D77: AP-073 | E77: services_postaux | F77: Réclamations | G77: Tous publics | H77: Réclamation courrier recommandé domestique non reçu | I77: Formulaire N°846 | J77: DÉLAI | K77: NON_TARIFAIRE | T77: 12 | W77: Délai : 1 an | X77: À compter du lendemain de la date de dépôt | Y77: 9 | AC77: UNVERIFIED_USER_SUPPLIED | AD77: FALSE | AE77: FALSE | AF77: Délai calendaire d'un an : ne pas assimiler à 365 jours (année bissextile)
A78: DZ_ALGERIE_POSTE | B78: Algérie Poste | C78: DZ | D78: AP-074 | E78: services_postaux | F78: Réclamations | G78: Tous publics | H78: Réclamation courrier recommandé international non reçu | I78: Formulaire CN08 | J78: DÉLAI | K78: NON_TARIFAIRE | T78: 6 | W78: Délai : 6 mois | X78: À compter du lendemain de la date de dépôt | Y78: 9 | AC78: UNVERIFIED_USER_SUPPLIED | AD78: FALSE | AE78: FALSE | AF78: Ne pas convertir automatiquement les 6 mois en un nombre fixe de jours
A79: DZ_ALGERIE_POSTE | B79: Algérie Poste | C79: DZ | D79: AP-075 | E79: services_postaux | F79: Codes postaux | G79: Tous publics | H79: Consultation du code postal | I79: www.poste.dz / guichet | J79: TARIF | K79: GRATUIT_EXPLICITE | L79: 0 | O79: Par consultation | W79: Gratuit | X79: Recherche sur poste.dz ou au bureau de poste de résidence | Y79: 9 | AC79: UNVERIFIED_USER_SUPPLIED | AD79: FALSE | AE79: FALSE | AF79: Obtenir document officiel, date et validation avant diffusion

Sheet 13_Couts_Annualises
A1: COÛTS COMPARABLES ET ÉQUIVALENTS ANNUELS
A2: Équivalents annuels analytiques lorsque prix fixe et périodicité sont explicites. Aucun ajustement de TVA ou de frais variables n'est ajouté. Les calculs ne prouvent pas la validité des tarifs transmis.
A4: ID origine | B4: Public | C4: Service | D4: Tarif source | E4: Montant source DA | F4: Fréquence / an | G4: Équivalent annuel DA | H4: Payeur | I4: Vérification | J4: Note / hypothèse
A5: AP-002 | B5: Particulier | C5: Compte CCP : tenue | D5: Gratuit | E5: 0 | F5: 1 | G5: =IF(F5="","",E5*F5) -> 0 | H5: Usager | I5: NON VÉRIFIÉ | J5: Gratuité annoncée ; coût fixe annualisé 0
A6: AP-009 | B6: Particulier | C6: Carte EDAHABIA : création ou renouvellement | D6: 350 DA | E6: 350 | F6: 0.5 | G6: =IF(F6="","",E6*F6) -> 175 | H6: Usager | I6: NON VÉRIFIÉ | J6: 350 DA / 2 ans → 175 DA par an équivalent analytique ; tarif réellement facturé = 350 DA
A7: AP-024 | B7: Particulier | C7: Retrait GAB Algérie Poste | D7: 30 DA | E7: 30 | G7: =IF(F7="","",E7*F7) | H7: Usager | I7: NON VÉRIFIÉ | J7: 30 DA par retrait ; le coût annuel dépend du nombre de retraits
A8: AP-025 | B8: Particulier | C8: Retrait GAB banque | D8: 35 DA | E8: 35 | G8: =IF(F8="","",E8*F8) | H8: Usager | I8: NON VÉRIFIÉ | J8: 35 DA par retrait ; le coût annuel dépend du nombre de retraits
A9: AP-052 | B9: Commerçant | C9: TPE mobile : abonnement complet | D9: 800 DA HT / mois | E9: 800 | F9: 12 | G9: =IF(F9="","",E9*F9) -> 9600 | H9: Commerçant | I9: NON VÉRIFIÉ | J9: 800 DA HT / mois, hors commission sur transactions
A10: AP-053 | B10: Commerçant | C10: TPE : commission variable | D10: Jusqu’à 1,50 % du montant | G10: =IF(F10="","",E10*F10) | H10: Commerçant | I10: NON VÉRIFIÉ | J10: Jusqu'à 1,5 % ; non calculable précisément sans barème
A11: AP-056 | B11: Particulier | C11: Abonnement boîte postale physique | D11: 1 000 DA / an | E11: 1000 | F11: 1 | G11: =IF(F11="","",E11*F11) -> 1000 | H11: Usager | I11: NON VÉRIFIÉ | J11: Loyer annuel
A12: AP-057 | B12: Entreprise | C12: Abonnement boîte postale morale | D12: 4 200 DA / an | E12: 4200 | F12: 1 | G12: =IF(F12="","",E12*F12) -> 4200 | H12: Usager | I12: NON VÉRIFIÉ | J12: Loyer annuel
A13: AP-061 | B13: Particulier | C13: BaridiMob : adhésion | D13: 50 DA | E13: 50 | G13: =IF(F13="","",E13*F13) | H13: Usager | I13: NON VÉRIFIÉ | J13: Ponctuel ; ne pas comptabiliser comme récurrence
A14: AP-062 | B14: Particulier | C14: BaridiMob : virement | D14: 12 à 24 DA / virement | E14: 12 | G14: =IF(F14="","",E14*F14) | H14: Usager | I14: NON VÉRIFIÉ | J14: 12 à 24 DA selon tranche ; pas de tarif unique
A15: AP-063 | B15: Particulier | C15: BaridiMob : abonnement | D15: 50 DA / mois | E15: 50 | F15: 12 | G15: =IF(F15="","",E15*F15) -> 600 | H15: Usager | I15: NON VÉRIFIÉ | J15: 50 DA / mois si actif
A16: AP-066 | B16: Tous publics | C16: Poste restante : journal | D16: 30 DA | E16: 30 | G16: =IF(F16="","",E16*F16) | H16: Usager | I16: NON VÉRIFIÉ | J16: 30 DA selon opération ; unité de facturation à confirmer
A17: AP-068 | B17: Tous publics | C17: Poste restante : abonnement | D17: 2 000 DA / an | E17: 2000 | F17: 1 | G17: =IF(F17="","",E17*F17) -> 2000 | H17: Usager | I17: NON VÉRIFIÉ | J17: 2 000 DA par an

Sheet 14_Dictionnaire_API
A1: DICTIONNAIRE TECHNIQUE DE DONNÉES — FINCLUDIA
A2: Champs normalisés de l'onglet 12. Conventions : nombre décimal, champ absent = cellule vide, ID stable, source et date obligatoires pour publication.
A4: Champ | B4: Type | C4: Exemple | D4: Usage | E4: Contrôle d'intégrité
A5: provider_id | B5: String | C5: DZ_ALGERIE_POSTE | D5: Identifiant stable de l'organisme | E5: Toujours identique
A6: service_id | B6: String | C6: AP-009 | D6: Identifiant stable unique de la condition | E6: Ne pas réutiliser
A7: service_family | B7: Enum | C7: cartes_monetique_locale | D7: Famille comparable FINCLUDIA | E7: Mapping évolutif
A8: subfamily | B8: String | C8: Émission carte | D8: Sous-famille fonctionnelle | E8: Séparer produit / opération
A9: customer_segment | B9: String | C9: Particulier | D9: Particulier, commerçant, société ou tous publics | E9: Ne pas inventer de profil
A10: operation_channel | B10: String | C10: GAB / Guichet / TPE | D10: Canal d'exécution | E10: Une opération peut dépendre du canal
A11: entry_kind | B11: Enum | C11: TARIF / PLAFOND / DÉLAI / PROCÉDURE | D11: Nature de l'information | E11: Ne pas assimiler plafond à prix
A12: fee_mode | B12: Enum | C12: FIXE_DÉCLARÉ | D12: Mode de calcul du frais | E12: Barème incomplet => aucun calcul
A13: fee_amount_dzd | B13: Decimal | C13: 350 | D13: Montant fixe déclaré | E13: Null si non renseigné
A14: fee_amount_max_dzd | B14: Decimal | C14: 24 | D14: Borne haute d'une fourchette | E14: Non assimilé au tarif exact
A15: fee_rate_max | B15: Decimal | C15: 0.015 | D15: Taux plafond 1,50 % (décimal) | E15: Ne pas traiter comme taux appliqué
... A30: auto_compute | B30: Boolean | C30: FALSE | D30: Calcul automatique d'un tarif | E30: Conditions de calcul suffisantes

Sheet 15_Sources_Provenance
A1: SOURCES, DATES ET TRAÇABILITÉ DES DONNÉES
A2: Les trois sections ont été fournies directement dans le message utilisateur. Aucune date d'application ni document officiel tarifaire n'accompagne le texte ; le lien poste.dz cité n'a pas servi à vérifier les prix.
A4: ID source | B4: Bloc transmis | C4: Localisation / lien | D4: Nature de la preuve | E4: Périmètre de la source
A5: SRC-001 | B5: Section 7 — Services financiers (CCP) | C5: Texte communiqué dans cette conversation | D5: Informations utilisateur, sans brochure officielle jointe | E5: Frais et procédures CCP, Western Union entrant, comptes, épargne
A6: SRC-002 | B6: Section 8 — Services monétiques (EDAHABIA) | C6: Texte communiqué dans cette conversation | D6: Informations utilisateur, sans brochure officielle jointe | E6: Carte, GAB, TPE, e-paiement, réclamations, RIP/NIP
A7: SRC-003 | B7: Section 9 — Réseau postal | C7: Texte communiqué dans cette conversation | D7: Informations utilisateur, sans brochure officielle jointe | E7: Boîtes postales, TPE, BaridiMob, courrier, philatélie
A8: SRC-004 | B8: Site d'Algérie Poste cité dans texte | C8: https://www.poste.dz/ | D8: URL de consultation uniquement, pas de tarif extrait directement du site | E8: Le site est indiqué pour les codes postaux ; aucun contrôle externe réalisé

Sheet 00_Tableau_de_bord
A1: ALGÉRIE POSTE / CCP — SOCLE SPÉCIAL FINCLUDIA
A2: Base de données thématique extraite exclusivement du texte transmis ; à valider auprès d'Algérie Poste avant diffusion publique. Distinction obligatoire : tarif ≠ plafond ≠ délai ≠ procédure.
A4: Indicateur | B4: Résultat | C4: Méthode | D4: Statut source
A5: Services / règles uniques | B5: =COUNTA('01_Referentiel_Unique'!A5:A79) -> 75 | C5: Nombre de lignes dans le référentiel | D5: Texte utilisateur
A6: Lignes tarifaires | B6: =COUNTIF('01_Referentiel_Unique'!G5:G79,"TARIF") -> 46 | C6: Nature de l'information = TARIF
A7: Plafonds d'opérations | B7: =COUNTIF('01_Referentiel_Unique'!G5:G79,"PLAFOND") -> 4 | C7: Nature = PLAFOND
A8: Délais de réclamation | B8: =COUNTIF('01_Referentiel_Unique'!G5:G79,"DÉLAI") -> 7 | C8: Nature = DÉLAI
A9: Lignes gratuites annoncées | B9: =COUNTIF('01_Referentiel_Unique'!H5:H79,"Gratuit")+COUNTIF('01_Referentiel_Unique'!H5:H79,"Gratuit pour le porteur") -> 13 | C9: Libellé commence par Gratuit
A10: Contrôles documentaires requis | B10: 16 | C10: Registre de vérification | D10: Ouverts
A13: Famille | B13: Nb fiches | C13: Type de comparateur | D13: Public principal
A14: CCP & services financiers | B14: =COUNTIF('01_Referentiel_Unique'!B5:B79,A14) -> 18 | C14: Comptes, caisse, virements, épargne | D14: Particulier
A15: Monétique EDAHABIA | B15: =COUNTIF('01_Referentiel_Unique'!B5:B79,A15) -> 25 | C15: Carte locale, paiements, retraits | D15: Porteur
A16: Monétique TPE commerçants | B16: =COUNTIF('01_Referentiel_Unique'!B5:B79,A16) -> 8 | C16: TPE et e-encaissement | D16: Professionnel / Entreprise
A17: Services numériques | B17: =COUNTIF('01_Referentiel_Unique'!B5:B79,A17) -> 5 | C17: BaridiMob, E-CCP | D17: Particulier
A18: Réseau et services postaux | B18: =COUNTIF('01_Referentiel_Unique'!B5:B79,A18) -> 14 | C18: Postaux complémentaires | D18: Particulier / Entreprise
A19: Identifiants et référentiels | B19: =COUNTIF('01_Referentiel_Unique'!B5:B79,A19) -> 4 | C19: Documents / pédagogie | D19: Tous publics
A20: International - remise reçue | B20: =COUNTIF('01_Referentiel_Unique'!B5:B79,A20) -> 1 | C20: Paiement WU entrant en DZD | D20: Tous publics
A23: Feuille | B23: Utilité | C23: Unité / public | D23: Précaution de lecture
A24: 01_Referentiel_Unique | B24: 75 fiches uniques — base canonique | C24: Tous publics | D24: Tarif/plafond/procédure distincts
A25: 02_CCP_Comptes | B25: Comptes, guichets, chèques, virements, épargne | C25: Particulier | D25: Comparer seulement les services réellement documentés
A26: 03_EDAHABIA | B26: Carte locale, DAB/GAB, litiges | C26: Porteur | D26: La durée 2 ans nécessite une preuve
A27: 04_TPE_Commercants | B27: Abonnement et commissions commerçants | C27: Pro / Entreprise | D27: Ne pas compter deux fois les trois composantes
A28: 05_Reseau_Postal | B28: Boîtes postales et courrier | C28: Tous publics | D28: Hors comparateur des comptes bancaires
A29: 06_BaridiMob_ECCP | B29: Services numériques, virements | C29: Particulier | D29: Tranches de virement à documenter
A30: 07_Identifiants_WU | B30: RIP/NIP, Western Union entrant | C30: Tous publics | D30: WU ne signifie pas virement sortant CCP
A31: 08_Plafonds_Delais | B31: Minima, maxima, délais de recours | C31: Tous publics | D31: Les délais ne sont pas des frais
A32: 09_Bareme_PINPAD | B32: Tranches source du PIN PAD | C32: Particulier | D32: Calcul automatique bloqué
A33: 10_Matrice_FINCLUDIA | B33: Couverture des rubriques du comparateur | C33: Produit / technique | D33: Catégories non documentées séparées
A34: 11_Controle_Validation | B34: 16 contrôles pré-publication | C34: Équipe métier | D34: Aucune validation officielle effectuée
... A38: 15_Sources_Provenance | B38: Source, date, fiabilité | C38: Métier / conformité | D38: Texte utilisateur uniquement
A41: Règle FINCLUDIA : ne publier que les conditions dont la source officielle, la date d'effet et la preuve de validation sont disponibles. Ne jamais remplacer « non documenté » par « gratuit » ou « produit inexistant ».
